Workbook

Sheet YTD ummary
B2: NOIR Cinemas - Unaizah
B3: Managed & Operated by - Mukta A2 Cinemas
B5: Cinema | D5: Noir Cinema | K5: Financial | L5: 2026 - 27
B6: Location | D6: Unaizah | K6: VAT | L6: 0.15
B7: Screens | D7: 4 | K7: GCAM | L7: 0.1
B8: Seats | D8: 238
B10: Month | C10: Admits | D10: ATP | E10: OCC% | F10: GBO Rev | G10: G-Conc Rev | H10: SPH | I10: ASR | J10: Conversion | K10: COGS % | L10: Total Revenue
B11: YTD | C11: =C26 -> 23849 | D11: =+D26 -> 31.123242 | E11: =E26 -> 0 | F11: =+F26 -> 742258.2 | G11: =+G26 -> 375587.7 | H11: =+H26 -> 15.748572 | I11: =I26 -> 0 | J11: =J26 -> 0 | K11: =K26 -> 0 | L11: =+L26 -> 1117845.9
B12: Budgeted | C12: 31000 | D12: - | E12: - | F12: 1038500 | G12: 744000 | H12: - | I12: - | J12: - | K12: - | L12: =F12+G12 -> 1782500
B13: Achived % | C13: =C11/C12 -> 0.76932258 | D13: - | E13: - | F13: =F11/F12 -> 0.71474068 | G13: =G11/G12 -> 0.50482218 | H13: =H11/H12 -> #VALUE! | I13: - | J13: - | K13: - | L13: =L11/L12 -> 0.62712252
B14: 46023 | C14: ='Jan 2026'!G44 -> 1265 | D14: ='Jan 2026'!I44 -> 33.501976 | E14: ='Jan 2026'!J44 -> 0.038119632 | F14: ='Jan 2026'!H44 -> 42380 | G14: ='Jan 2026'!P44 -> 22104 | H14: ='Jan 2026'!Q44 -> 17.473518 | I14: ='Jan 2026'!S44 -> 0.52964427 | J14: ='Jan 2026'!W44 -> 1.1272727 | K14: ='Jan 2026'!Y44 -> 0.19954216 | L14: =F14+G14 -> 64484
B15: 46054 | C15: ='Feb 2026'!G41 -> 462 | D15: ='Feb 2026'!I41 -> 27.277056 | E15: ='Feb 2026'!J41 -> 0.021174206 | F15: ='Feb 2026'!H41 -> 12602 | G15: ='Feb 2026'!P41 -> 12145.78 | H15: ='Feb 2026'!Q41 -> 26.289567 | I15: ='Feb 2026'!S41 -> 0.80519481 | J15: ='Feb 2026'!W41 -> 1.538961 | K15: ='Feb 2026'!Y41 -> 0.19152907 | L15: =F15+G15 -> 24747.78
B16: 46082 | C16: ='Mar2026'!G44 -> 3809 | D16: ='Mar2026'!I44 -> 33.756367 | E16: ='Mar2026'!J44 -> 0.15543132 | F16: ='Mar2026'!H44 -> 128578 | G16: ='Mar2026'!P44 -> 68528 | H16: ='Mar2026'!Q44 -> 17.991074 | I16: ='Mar2026'!S44 -> 0.40535574 | J16: ='Mar2026'!W44 -> 0.93279076 | K16: ='Mar2026'!Y44 -> 0.18068235 | L16: =F16+G16 -> 197106
B17: 46113 | C17: ='Apr2026'!G44 -> 3689 | D17: ='Apr2026'!I44 -> 33.479751 | E17: ='Apr2026'!J44 -> 0.10655998 | F17: ='Apr2026'!H44 -> 123506.8 | G17: ='Apr2026'!P44 -> 50049.53 | H17: ='Apr2026'!Q44 -> 13.567235 | I17: ='Apr2026'!S44 -> 0.32176742 | J17: ='Apr2026'!W44 -> 0.70777989 | K17: ='Apr2026'!Y44 -> 0.17203418 | L17: =F17+G17 -> 173556.33
B18: 46143 | C18: ='May 2026'!G44 -> 4122 | D18: ='May 2026'!I44 -> 33.41853 | E18: ='May 2026'!J44 -> 0.12690496 | F18: ='May 2026'!H44 -> 137751.18 | G18: ='May 2026'!P44 -> 53778.71 | H18: ='May 2026'!Q44 -> 13.046752 | I18: ='May 2026'!S44 -> 0.33357593 | J18: ='May 2026'!W44 -> 0.63731198 | K18: ='May 2026'!Y44 -> 0.19948452 | L18: =F18+G18 -> 191529.89
B19: 46174 | C19: ='Jun 2026'!G44 -> 1990 | D19: ='Jun 2026'!I44 -> 26.338693 | E19: ='Jun 2026'!J44 -> 0.059757965 | F19: ='Jun 2026'!H44 -> 52414 | G19: ='Jun 2026'!P44 -> 36984.27 | H19: ='Jun 2026'!Q44 -> 18.58506 | I19: ='Jun 2026'!S44 -> 0.43567839 | J19: ='Jun 2026'!W44 -> 0.90552764 | K19: ='Jun 2026'!Y44 -> 0.19599954 | L19: =F19+G19 -> 89398.27
B20: 46204 | C20: ='Jul 2026'!G44 -> 2303 | D20: ='Jul 2026'!I44 -> 22.201259 | E20: ='Jul 2026'!J44 -> 0.065398268 | F20: ='Jul 2026'!H44 -> 51129.5 | G20: ='Jul 2026'!P44 -> 46102.47 | H20: ='Jul 2026'!Q44 -> 20.018441 | I20: ='Jul 2026'!S44 -> 0.44767694 | J20: ='Jul 2026'!W44 -> 0.93617021 | K20: ='Jul 2026'!Y44 -> 0.19380176 | L20: =F20+G20 -> 97231.97
B21: 46235 | C21: ='Aug 2026'!G44 -> 4624 | D21: ='Aug 2026'!I44 -> 30.719446 | E21: ='Aug 2026'!J44 -> 0.138813 | F21: ='Aug 2026'!H44 -> 142046.72 | G21: ='Aug 2026'!P44 -> 60976.94 | H21: ='Aug 2026'!Q44 -> 13.187054 | I21: ='Aug 2026'!S44 -> 0.3300173 | J21: ='Aug 2026'!W44 -> 0.57266436 | K21: ='Aug 2026'!Y44 -> 0.18643868 | L21: =F21+G21 -> 203023.66
B22: 46266 | C22: ='Sep 2026'!G43 -> 1491 | D22: ='Sep 2026'!I43 -> 32.279007 | E22: ='Sep 2026'!J43 -> 0.046242595 | F22: ='Sep 2026'!H43 -> 48128 | G22: ='Sep 2026'!P43 -> 22398 | H22: ='Sep 2026'!Q43 -> 15.022133 | I22: ='Sep 2026'!S43 -> 0.38564722 | J22: ='Sep 2026'!W43 -> 0.64185111 | K22: ='Sep 2026'!Y43 -> 0.16997678 | L22: =F22+G22 -> 70526
B23: 46296 | C23: ='Oct 2026'!G44 -> 94 | D23: ='Oct 2026'!I44 -> 39.595745 | E23: ='Oct 2026'!J44 -> 0.04752275 | F23: ='Oct 2026'!H44 -> 3722 | G23: ='Oct 2026'!P44 -> 2520 | H23: ='Oct 2026'!Q44 -> 26.808511 | I23: ='Oct 2026'!S44 -> 0.63829787 | J23: ='Oct 2026'!W44 -> 1.2765957 | K23: ='Oct 2026'!Y44 -> 0.16684921 | L23: =F23+G23 -> 6242
B24: 46327 | C24: 0 | D24: 0 | E24: ='MTD Summary'!E55 -> 0 | F24: 0 | G24: 0 | H24: 0 | I24: 0 | J24: 0 | K24: 0 | L24: =F24+G24 -> 0
B25: 46357 | C25: 0 | D25: 0 | E25: ='MTD Summary'!E56 -> 0 | F25: 0 | G25: 0 | H25: 0 | I25: 0 | J25: 0 | K25: 0 | L25: =F25+G25 -> 0
B26: TOTAL | C26: =SUM(C14:C25) -> 23849 | D26: =F26/C26 -> 31.123242 | E26: ='MTD Summary'!E44 -> 0 | F26: =SUM(F14:F25) -> 742258.2 | G26: =SUM(G14:G25) -> 375587.7 | H26: =G26/C26 -> 15.748572 | I26: ='MTD Summary'!I44 -> 0 | J26: ='MTD Summary'!J44 -> 0 | K26: ='MTD Summary'!K44 -> 0 | L26: =SUM(L14:L25) -> 1117845.9

Sheet MTD Summary
B2: NOIR Cinemas -Unaizah
B3: Managed & Operated by - Mukta A2 Cinemas
B5: Cinema | D5: Noir Cinema | K5: Month | L5: 46296
B6: Location | D6: Unaizah | K6: Financial | L6: 2026
B7: Screens | D7: 4 | K7: VAT | L7: 0.15
B8: Seats | D8: 238 | K8: GCAM | L8: 0.1
B10: Date | C10: Admits | D10: ATP | E10: OCC% | F10: GBO Rev | G10: G-Conc Rev | H10: SPH | I10: ASR | J10: Conversion | K10: COGS % | L10: Total Revenue
B11: MTD | C11: =C44 -> 0 | D11: =D44 -> 0 | E11: =E44 -> 0 | F11: =F44 -> 0 | G11: =G44 -> 0 | H11: =H44 -> 0 | I11: =I44 -> 0 | J11: =J44 -> 0 | ... L11: =L44 -> 0
B12: Budgeted | C12: 0 | D12: - | E12: - | F12: 0 | G12: 0 | H12: - | I12: - | J12: - | K12: - | L12: =F12+G12 -> 0
B13: Achieved % | C13: =C11/C12 -> #DIV/0! | D13: - | E13: - | F13: =F11/F12 -> #DIV/0! | G13: =G11/G12 -> #DIV/0! | H13: - | I13: - | J13: - | K13: - | L13: =L11/L12 -> #DIV/0!
B14: 46296 | C14: ='Oct 2026'!G13 -> 55 | D14: ='Oct 2026'!H13 -> 2180 | E14: ='Oct 2026'!I13 -> 39.636364 | F14: ='Oct 2026'!J13 -> 0.055611729 | G14: ='Oct 2026'!K13 -> 284.34783 | H14: ='Oct 2026'!L13 -> 1895.6522 | I14: ='Oct 2026'!M13 -> 176.33 | J14: ='Oct 2026'!N13 -> 1719.3222 | ... L14: ='Oct 2026'!P13 -> 1277
B15: 46297 | C15: ='Oct 2026'!G14 -> 39 | D15: ='Oct 2026'!H14 -> 1542 | E15: ='Oct 2026'!I14 -> 39.538462 | F15: ='Oct 2026'!J14 -> 0.039433771 | G15: ='Oct 2026'!K14 -> 201.13043 | H15: ='Oct 2026'!L14 -> 1340.8696 | I15: ='Oct 2026'!M14 -> 95.99 | J15: ='Oct 2026'!N14 -> 1244.8796 | ... L15: ='Oct 2026'!P14 -> 1243
B16: 46298 | C16: ='Oct 2026'!G15 -> 0 | D16: ='Oct 2026'!H15 -> 0 | E16: ='Oct 2026'!I15 -> 0 | F16: ='Oct 2026'!J15 -> 0 | G16: ='Oct 2026'!K15 -> 0 | H16: ='Oct 2026'!L15 -> 0 | I16: ='Oct 2026'!M15 -> 0 | J16: ='Oct 2026'!N15 -> 0 | ... L16: ='Oct 2026'!P15 -> 0
B17: 46299 | C17: ='Oct 2026'!G16 -> 0 | D17: ='Oct 2026'!H16 -> 0 | E17: ='Oct 2026'!I16 -> 0 | F17: ='Oct 2026'!J16 -> 0 | G17: ='Oct 2026'!K16 -> 0 | H17: ='Oct 2026'!L16 -> 0 | I17: ='Oct 2026'!M16 -> 0 | J17: ='Oct 2026'!N16 -> 0 | ... L17: ='Oct 2026'!P16 -> 0
B18: 46300 | C18: ='Oct 2026'!G17 -> 0 | D18: ='Oct 2026'!H17 -> 0 | E18: ='Oct 2026'!I17 -> 0 | F18: ='Oct 2026'!J17 -> 0 | G18: ='Oct 2026'!K17 -> 0 | H18: ='Oct 2026'!L17 -> 0 | I18: ='Oct 2026'!M17 -> 0 | J18: ='Oct 2026'!N17 -> 0 | ... L18: ='Oct 2026'!P17 -> 0
B19: 46301 | C19: ='Oct 2026'!G18 -> 0 | D19: ='Oct 2026'!H18 -> 0 | E19: ='Oct 2026'!I18 -> 0 | F19: ='Oct 2026'!J18 -> 0 | G19: ='Oct 2026'!K18 -> 0 | H19: ='Oct 2026'!L18 -> 0 | I19: ='Oct 2026'!M18 -> 0 | J19: ='Oct 2026'!N18 -> 0 | ... L19: ='Oct 2026'!P18 -> 0
B20: 46302 | C20: ='Oct 2026'!G19 -> 0 | D20: ='Oct 2026'!H19 -> 0 | E20: ='Oct 2026'!I19 -> 0 | F20: ='Oct 2026'!J19 -> 0 | G20: ='Oct 2026'!K19 -> 0 | H20: ='Oct 2026'!L19 -> 0 | I20: ='Oct 2026'!M19 -> 0 | J20: ='Oct 2026'!N19 -> 0 | ... L20: ='Oct 2026'!P19 -> 0
B21: 46303 | C21: ='Oct 2026'!G20 -> 0 | D21: ='Oct 2026'!H20 -> 0 | E21: ='Oct 2026'!I20 -> 0 | F21: ='Oct 2026'!J20 -> 0 | G21: ='Oct 2026'!K20 -> 0 | H21: ='Oct 2026'!L20 -> 0 | I21: ='Oct 2026'!M20 -> 0 | J21: ='Oct 2026'!N20 -> 0 | ... L21: ='Oct 2026'!P20 -> 0
B22: 46304 | C22: ='Oct 2026'!G21 -> 0 | D22: ='Oct 2026'!H21 -> 0 | E22: ='Oct 2026'!I21 -> 0 | F22: ='Oct 2026'!J21 -> 0 | G22: ='Oct 2026'!K21 -> 0 | H22: ='Oct 2026'!L21 -> 0 | I22: ='Oct 2026'!M21 -> 0 | J22: ='Oct 2026'!N21 -> 0 | ... L22: ='Oct 2026'!P21 -> 0
B23: 46305 | C23: ='Oct 2026'!G22 -> 0 | D23: ='Oct 2026'!H22 -> 0 | E23: ='Oct 2026'!I22 -> 0 | F23: ='Oct 2026'!J22 -> 0 | G23: ='Oct 2026'!K22 -> 0 | H23: ='Oct 2026'!L22 -> 0 | I23: ='Oct 2026'!M22 -> 0 | J23: ='Oct 2026'!N22 -> 0 | ... L23: ='Oct 2026'!P22 -> 0
B24: 46306 | C24: ='Oct 2026'!G23 -> 0 | D24: ='Oct 2026'!H23 -> 0 | E24: ='Oct 2026'!I23 -> 0 | F24: ='Oct 2026'!J23 -> 0 | G24: ='Oct 2026'!K23 -> 0 | H24: ='Oct 2026'!L23 -> 0 | I24: ='Oct 2026'!M23 -> 0 | J24: ='Oct 2026'!N23 -> 0 | ... L24: ='Oct 2026'!P23 -> 0
B25: 46307 | C25: ='Oct 2026'!G24 -> 0 | D25: ='Oct 2026'!H24 -> 0 | E25: ='Oct 2026'!I24 -> 0 | F25: ='Oct 2026'!J24 -> 0 | G25: ='Oct 2026'!K24 -> 0 | H25: ='Oct 2026'!L24 -> 0 | I25: ='Oct 2026'!M24 -> 0 | J25: ='Oct 2026'!N24 -> 0 | ... L25: ='Oct 2026'!P24 -> 0
... B43: 46325 | C43: ='Oct 2026'!G42 -> 0 | D43: ='Oct 2026'!H42 -> 0 | E43: ='Oct 2026'!I42 -> 0 | F43: ='Oct 2026'!J42 -> 0 | G43: ='Oct 2026'!K42 -> 0 | H43: ='Oct 2026'!L42 -> 0 | I43: ='Oct 2026'!M42 -> 0 | J43: ='Oct 2026'!N42 -> 0 | ... L43: ='Oct 2026'!P42 -> 0
B44: 46326 | C44: 0 | D44: 0 | E44: 0 | F44: 0 | H44: 0 | I44: 0 | J44: 0 | K44: 0 | L44: 0

Sheet Jan 2026
B2: NOIR Cinemas - Unaizah
B3: Managed & Operated by - Mukta A2 Cinemas
B5: Cinema | D5: Noir Cinema | G5: Month | I5: 46023
B6: Location | D6: Unizah | G6: Financial Year | I6: 2026
B7: Screens | D7: 4 | G7: VAT | I7: 0.15
B8: Seats | D8: 238 | G8: GCAM | I8: 0.1
G10: Box Office | P10: Concession | AA10: Total Box Office Revenue | AC10: Total Concession Revenue | AE10: Grand Total Revenue
B11: Date | C11: Day | D11: Seats | E11: Total Shows | F11: Total Available Capacity | G11: Admits | H11: Box Office Revenue | I11: ATP | J11: Occ % | K11: VAT (15%) | L11: Net BO Rev Before GCAM | M11: GCAM | N11: Net BO Rev After GCAM | P11: Concession Rev | Q11: SPH | R11: Transaction | S11: ASR | T11: VAT | U11: Net Concession Revenue | V11: Items Sold | W11: Concession Conversion % | X11: Concessions Standard Cost | Y11: COGS | AA11: Gross | AB11: Nett | AC11: Gross | AD11: Nett | AE11: Gross | AF11: Nett
B12: TOTAL MTD | D12: =D44 -> 238 | E12: =E44 -> 562 | F12: =F44 -> 33185 | G12: =G44 -> 1265 | H12: =H44 -> 42380 | I12: =I44 -> 33.501976 | J12: =J44 -> 0.038119632 | K12: =K44 -> 5527.8261 | ... N12: =N44 -> 33473.044 | P12: =P44 -> 22104 | Q12: =Q44 -> 17.473518 | R12: =R44 -> 670 | S12: =S44 -> 0.52964427 | T12: =T44 -> 2883.1304 | U12: =U44 -> 19220.87 | V12: =V44 -> 1426 | W12: =W44 -> 1.1272727 | ... Y12: =Y44 -> 0.19954216 | AA12: =AA44 -> 42380 | AB12: =AB44 -> 33473.044 | AC12: =AC44 -> 22104 | AD12: =AD44 -> 19220.87 | AE12: =AE44 -> 64484 | AF12: =AF44 -> 52693.913
B13: 46023 | C13: Thursday | D13: 238 | E13: 17 | F13: 1016 | G13: 90 | H13: 3010 | I13: =H13/G13 -> 33.444444 | J13: =G13/F13 -> 0.088582677 | K13: =H13*15/115 -> 392.6087 | L13: =H13-K13 -> 2617.3913 | M13: 231.15 | N13: =L13-M13 -> 2386.2413 | P13: 1203 | Q13: =P13/G13 -> 13.366667 | R13: 33 | S13: =(R13/G13) -> 0.36666667 | T13: =P13*15/115 -> 156.91304 | U13: =P13-T13 -> 1046.087 | V13: 61 | W13: =V13/G13 -> 0.67777778 | X13: 252.53 | Y13: =(X13/P13) -> 0.20991687 | AA13: =H13 -> 3010 | AB13: =N13 -> 2386.2413 | AC13: =P13 -> 1203 | AD13: =U13 -> 1046.087 | AE13: =AA13+AC13 -> 4213 | AF13: =AB13+AD13 -> 3432.3283 | AG13: `
B14: 46024 | C14: Friday | D14: 238 | E14: 17 | F14: 1016 | G14: 63 | H14: 2146 | I14: =H14/G14 -> 34.063492 | J14: =G14/F14 -> 0.062007874 | K14: =H14*15/115 -> 279.91304 | L14: =H14-K14 -> 1866.087 | M14: 181.06 | N14: =L14-M14 -> 1685.027 | P14: 948 | Q14: =P14/G14 -> 15.047619 | R14: 27 | S14: =(R14/G14) -> 0.42857143 | T14: =P14*15/115 -> 123.65217 | U14: =P14-T14 -> 824.34783 | V14: 55 | W14: =V14/G14 -> 0.87301587 | X14: 174.62 | Y14: =(X14/P14) -> 0.18419831 | AA14: =H14 -> 2146 | AB14: =N14 -> 1685.027 | AC14: =P14 -> 948 | AD14: =U14 -> 824.34783 | AE14: =AA14+AC14 -> 3094 | AF14: =AB14+AD14 -> 2509.3748
B15: 46025 | C15: Saturday | D15: 238 | E15: 17 | F15: 1016 | G15: 31 | H15: 992 | I15: =H15/G15 -> 32 | J15: =G15/F15 -> 0.030511811 | K15: =H15*15/115 -> 129.3913 | L15: =H15-K15 -> 862.6087 | M15: 86.27 | N15: =L15-M15 -> 776.3387 | P15: 374 | Q15: =P15/G15 -> 12.064516 | R15: 12 | S15: =(R15/G15) -> 0.38709677 | T15: =P15*15/115 -> 48.782609 | U15: =P15-T15 -> 325.21739 | V15: 22 | W15: =V15/G15 -> 0.70967742 | X15: 64.26 | Y15: =(X15/P15) -> 0.17181818 | AA15: =H15 -> 992 | AB15: =N15 -> 776.3387 | AC15: =P15 -> 374 | AD15: =U15 -> 325.21739 | AE15: =AA15+AC15 -> 1366 | AF15: =AB15+AD15 -> 1101.5561
B16: 46026 | C16: Sunday | D16: 238 | E16: 17 | F16: 1016 | G16: 17 | H16: 594 | I16: =H16/G16 -> 34.941176 | J16: =G16/F16 -> 0.016732283 | K16: =H16*15/115 -> 77.478261 | L16: =H16-K16 -> 516.52174 | M16: 43.31 | N16: =L16-M16 -> 473.21174 | P16: 573 | Q16: =P16/G16 -> 33.705882 | R16: 11 | S16: =(R16/G16) -> 0.64705882 | T16: =P16*15/115 -> 74.73913 | U16: =P16-T16 -> 498.26087 | V16: 29 | W16: =V16/G16 -> 1.7058824 | X16: 120.05 | Y16: =(X16/P16) -> 0.20951134 | AA16: =H16 -> 594 | AB16: =N16 -> 473.21174 | AC16: =P16 -> 573 | AD16: =U16 -> 498.26087 | AE16: =AA16+AC16 -> 1167 | AF16: =AB16+AD16 -> 971.47261
B17: 46027 | C17: Monday | D17: 238 | E17: 17 | F17: 1016 | G17: 31 | H17: 992 | I17: =H17/G17 -> 32 | J17: =G17/F17 -> 0.030511811 | K17: =H17*15/115 -> 129.3913 | L17: =H17-K17 -> 862.6087 | M17: 80.71 | N17: =L17-M17 -> 781.8987 | P17: 662 | Q17: =P17/G17 -> 21.354839 | R17: 22 | S17: =(R17/G17) -> 0.70967742 | T17: =P17*15/115 -> 86.347826 | U17: =P17-T17 -> 575.65217 | V17: 30 | W17: =V17/G17 -> 0.96774194 | X17: 132.31 | Y17: =(X17/P17) -> 0.19986405 | AA17: =H17 -> 992 | AB17: =N17 -> 781.8987 | AC17: =P17 -> 662 | AD17: =U17 -> 575.65217 | AE17: =AA17+AC17 -> 1654 | AF17: =AB17+AD17 -> 1357.5509
B18: 46028 | C18: Tuesday | D18: 238 | E18: 17 | F18: 1016 | G18: 22 | H18: 724 | I18: =H18/G18 -> 32.909091 | J18: =G18/F18 -> 0.021653543 | K18: =H18*15/115 -> 94.434783 | L18: =H18-K18 -> 629.56522 | M18: 62.96 | N18: =L18-M18 -> 566.60522 | P18: 332 | Q18: =P18/G18 -> 15.090909 | R18: 8 | S18: =(R18/G18) -> 0.36363636 | T18: =P18*15/115 -> 43.304348 | U18: =P18-T18 -> 288.69565 | V18: 19 | W18: =V18/G18 -> 0.86363636 | X18: 79.34 | Y18: =(X18/P18) -> 0.2389759 | AA18: =H18 -> 724 | AB18: =N18 -> 566.60522 | AC18: =P18 -> 332 | AD18: =U18 -> 288.69565 | AE18: =AA18+AC18 -> 1056 | AF18: =AB18+AD18 -> 855.30087
B19: 46029 | C19: Wednesday | D19: 238 | E19: 17 | F19: 1016 | G19: 41 | H19: 1332 | I19: =H19/G19 -> 32.487805 | J19: =G19/F19 -> 0.040354331 | K19: =H19*15/115 -> 173.73913 | L19: =H19-K19 -> 1158.2609 | M19: 88.01 | N19: =L19-M19 -> 1070.2509 | P19: 596 | Q19: =P19/G19 -> 14.536585 | R19: 36 | S19: =(R19/G19) -> 0.87804878 | T19: =P19*15/115 -> 77.73913 | U19: =P19-T19 -> 518.26087 | V19: 78 | W19: =V19/G19 -> 1.902439 | X19: 156.3 | Y19: =(X19/P19) -> 0.26224832 | AA19: =H19 -> 1332 | AB19: =N19 -> 1070.2509 | AC19: =P19 -> 596 | AD19: =U19 -> 518.26087 | AE19: =AA19+AC19 -> 1928 | AF19: =AB19+AD19 -> 1588.5117
B20: 46030 | C20: Thursday | D20: 238 | E20: 20 | F20: 1190 | G20: 58 | H20: 1936 | I20: =H20/G20 -> 33.37931 | J20: =G20/F20 -> 0.048739496 | K20: =H20*15/115 -> 252.52174 | L20: =H20-K20 -> 1683.4783 | M20: 162.8 | N20: =L20-M20 -> 1520.6783 | P20: 1276 | Q20: =P20/G20 -> 22 | R20: 41 | S20: =(R20/G20) -> 0.70689655 | T20: =P20*15/115 -> 166.43478 | U20: =P20-T20 -> 1109.5652 | V20: 70 | W20: =V20/G20 -> 1.2068966 | X20: 218.51 | Y20: =(X20/P20) -> 0.17124608 | AA20: =H20 -> 1936 | AB20: =N20 -> 1520.6783 | AC20: =P20 -> 1276 | AD20: =U20 -> 1109.5652 | AE20: =AA20+AC20 -> 3212 | AF20: =AB20+AD20 -> 2630.2435
B21: 46031 | C21: Friday | D21: 238 | E21: 16 | F21: 952 | G21: 71 | H21: 2382 | I21: =H21/G21 -> 33.549296 | J21: =G21/F21 -> 0.074579832 | K21: =H21*15/115 -> 310.69565 | L21: =H21-K21 -> 2071.3043 | M21: 174.8 | N21: =L21-M21 -> 1896.5043 | P21: 1179 | Q21: =P21/G21 -> 16.605634 | R21: 31 | S21: =(R21/G21) -> 0.43661972 | T21: =P21*15/115 -> 153.78261 | U21: =P21-T21 -> 1025.2174 | V21: 68 | W21: =V21/G21 -> 0.95774648 | X21: 213.65 | Y21: =(X21/P21) -> 0.18121289 | AA21: =H21 -> 2382 | AB21: =N21 -> 1896.5043 | AC21: =P21 -> 1179 | AD21: =U21 -> 1025.2174 | AE21: =AA21+AC21 -> 3561 | AF21: =AB21+AD21 -> 2921.7217
B22: 46032 | C22: Saturday | D22: 238 | E22: 20 | F22: 1190 | G22: 61 | H22: 2002 | I22: =H22/G22 -> 32.819672 | J22: =G22/F22 -> 0.051260504 | K22: =H22*15/115 -> 261.13043 | L22: =H22-K22 -> 1740.8696 | M22: 137.93 | N22: =L22-M22 -> 1602.9396 | P22: 1006 | Q22: =P22/G22 -> 16.491803 | R22: 28 | S22: =(R22/G22) -> 0.45901639 | T22: =P22*15/115 -> 131.21739 | U22: =P22-T22 -> 874.78261 | V22: 65 | W22: =V22/G22 -> 1.0655738 | X22: 196.35 | Y22: =(X22/P22) -> 0.19517893 | AA22: =H22 -> 2002 | AB22: =N22 -> 1602.9396 | AC22: =P22 -> 1006 | AD22: =U22 -> 874.78261 | AE22: =AA22+AC22 -> 3008 | AF22: =AB22+AD22 -> 2477.7222
B23: 46033 | C23: Sunday | D23: 238 | E23: 20 | F23: 1190 | G23: 40 | H23: 1410 | I23: =H23/G23 -> 35.25 | J23: =G23/F23 -> 0.033613445 | K23: =H23*15/115 -> 183.91304 | L23: =H23-K23 -> 1226.087 | M23: 81.22 | N23: =L23-M23 -> 1144.867 | P23: 884 | Q23: =P23/G23 -> 22.1 | R23: 37 | S23: =(R23/G23) -> 0.925 | T23: =P23*15/115 -> 115.30435 | U23: =P23-T23 -> 768.69565 | V23: 75 | W23: =V23/G23 -> 1.875 | X23: 181.39 | Y23: =(X23/P23) -> 0.20519231 | AA23: =H23 -> 1410 | AB23: =N23 -> 1144.867 | AC23: =P23 -> 884 | AD23: =U23 -> 768.69565 | AE23: =AA23+AC23 -> 2294 | AF23: =AB23+AD23 -> 1913.5626
B24: 46034 | C24: Monday | D24: 238 | E24: 20 | F24: 1190 | G24: 33 | H24: 1056 | I24: =H24/G24 -> 32 | J24: =G24/F24 -> 0.027731092 | K24: =H24*15/115 -> 137.73913 | L24: =H24-K24 -> 918.26087 | M24: 58.44 | N24: =L24-M24 -> 859.82087 | P24: 770 | Q24: =P24/G24 -> 23.333333 | R24: 14 | S24: =(R24/G24) -> 0.42424242 | T24: =P24*15/115 -> 100.43478 | U24: =P24-T24 -> 669.56522 | V24: 69 | W24: =V24/G24 -> 2.0909091 | X24: 154.65 | Y24: =(X24/P24) -> 0.20084416 | AA24: =H24 -> 1056 | AB24: =N24 -> 859.82087 | AC24: =P24 -> 770 | AD24: =U24 -> 669.56522 | AE24: =AA24+AC24 -> 1826 | AF24: =AB24+AD24 -> 1529.3861
B25: 46035 | C25: Tuesday | D25: 238 | E25: 20 | F25: 1190 | G25: 23 | H25: 756 | I25: =H25/G25 -> 32.869565 | J25: =G25/F25 -> 0.019327731 | K25: =H25*15/115 -> 98.608696 | L25: =H25-K25 -> 657.3913 | M25: 49.05 | N25: =L25-M25 -> 608.3413 | P25: 1059 | Q25: =P25/G25 -> 46.043478 | R25: 30 | S25: =(R25/G25) -> 1.3043478 | T25: =P25*15/115 -> 138.13043 | U25: =P25-T25 -> 920.86957 | V25: 69 | W25: =V25/G25 -> 3 | X25: 224.45 | Y25: =(X25/P25) -> 0.21194523 | AA25: =H25 -> 756 | AB25: =N25 -> 608.3413 | AC25: =P25 -> 1059 | AD25: =U25 -> 920.86957 | AE25: =AA25+AC25 -> 1815 | AF25: =AB25+AD25 -> 1529.2109
... B32: 46042 | C32: Tuesday | D32: 238 | E32: 18 | F32: 1053 | G32: 18 | H32: 646 | I32: =H32/G32 -> 35.888889 | J32: =G32/F32 -> 0.017094017 | K32: =H32*15/115 -> 84.26087 | L32: =H32-K32 -> 561.73913 | M32: 56.18 | N32: =L32-M32 -> 505.55913 | P32: 620 | Q32: =P32/G32 -> 34.444444 | R32: 17 | S32: =(R32/G32) -> 0.94444444 | T32: =P32*15/115 -> 80.869565 | U32: =P32-T32 -> 539.13043 | V32: 34 | W32: =V32/G32 -> 1.8888889 | X32: 120.55 | Y32: =(X32/P32) -> 0.19443548 | AA32: =H32 -> 646 | AB32: =N32 -> 505.55913 | AC32: =P32 -> 620 | AD32: =U32 -> 539.13043 | AE32: =AA32+AC32 -> 1266 | AF32: =AB32+AD32 -> 1044.6896
B33: 46043 | C33: Wednesday | D33: 238 | E33: 18 | F33: 1053 | G33: 17 | H33: 544 | I33: =H33/G33 -> 32 | J33: =G33/F33 -> 0.016144349 | K33: =H33*15/115 -> 70.956522 | L33: =H33-K33 -> 473.04348 | M33: 41.75 | N33: =L33-M33 -> 431.29348 | P33: 218 | Q33: 18.76 | R33: 11 | S33: =(R33/G33) -> 0.64705882 | T33: =P33*15/115 -> 28.434783 | U33: =P33-T33 -> 189.56522 | V33: 30 | W33: =V33/G33 -> 1.7647059 | X33: 65.56 | Y33: =(X33/P33) -> 0.30073394 | AA33: =H33 -> 544 | AB33: =N33 -> 431.29348 | AC33: =P33 -> 218 | AD33: =U33 -> 189.56522 | AE33: =AA33+AC33 -> 762 | AF33: =AB33+AD33 -> 620.8587
B34: 46044 | C34: Thursday | D34: 238 | E34: 18 | F34: 1030 | G34: 104 | H34: 3538 | I34: =H34/G34 -> 34.019231 | J34: =G34/F34 -> 0.10097087 | K34: =H34*15/115 -> 461.47826 | L34: =H34-K34 -> 3076.5217 | M34: 302.11 | N34: =L34-M34 -> 2774.4117 | P34: 1157 | Q34: =P34/G34 -> 11.125 | R34: 30 | S34: =(R34/G34) -> 0.28846154 | T34: =P34*15/115 -> 150.91304 | U34: =P34-T34 -> 1006.087 | V34: 67 | W34: =V34/G34 -> 0.64423077 | X34: 217.08 | Y34: =(X34/P34) -> 0.18762316 | AA34: =H34 -> 3538 | AB34: =N34 -> 2774.4117 | AC34: =P34 -> 1157 | AD34: =U34 -> 1006.087 | AE34: =AA34+AC34 -> 4695 | AF34: =AB34+AD34 -> 3780.4987
B35: 46045 | C35: Friday | D35: 238 | E35: 19 | F35: 1110 | G35: 94 | H35: 3278 | I35: =H35/G35 -> 34.87234 | J35: =G35/F35 -> 0.084684685 | K35: =H35*15/115 -> 427.56522 | L35: =H35-K35 -> 2850.4348 | M35: 285.06 | N35: =L35-M35 -> 2565.3748 | P35: 721 | Q35: =P35/G35 -> 7.6702128 | R35: 25 | S35: =(R35/G35) -> 0.26595745 | T35: =P35*15/115 -> 94.043478 | U35: =P35-T35 -> 626.95652 | V35: 46 | W35: =V35/G35 -> 0.4893617 | X35: 119.83 | Y35: =(X35/P35) -> 0.16619972 | AA35: =H35 -> 3278 | AB35: =N35 -> 2565.3748 | AC35: =P35 -> 721 | AD35: =U35 -> 626.95652 | AE35: =AA35+AC35 -> 3999 | AF35: =AB35+AD35 -> 3192.3313
B36: 46046 | C36: Saturday | D36: 238 | E36: 19 | F36: 1110 | G36: 48 | H36: 1556 | I36: =H36/G36 -> 32.416667 | J36: =G36/F36 -> 0.043243243 | K36: =H36*15/115 -> 202.95652 | L36: =H36-K36 -> 1353.0435 | M36: 132.54 | N36: =L36-M36 -> 1220.5035 | P36: 611 | Q36: =P36/G36 -> 12.729167 | R36: 19 | S36: =(R36/G36) -> 0.39583333 | T36: =P36*15/115 -> 79.695652 | U36: =P36-T36 -> 531.30435 | V36: 36 | W36: =V36/G36 -> 0.75 | X36: 121.25 | Y36: =(X36/P36) -> 0.19844517 | AA36: =H36 -> 1556 | AB36: =N36 -> 1220.5035 | AC36: =P36 -> 611 | AD36: =U36 -> 531.30435 | AE36: =AA36+AC36 -> 2167 | AF36: =AB36+AD36 -> 1751.8078
B37: 46047 | C37: Sunday | D37: 238 | E37: 19 | F37: 1110 | G37: 12 | H37: 424 | I37: =H37/G37 -> 35.333333 | J37: =G37/F37 -> 0.010810811 | K37: =H37*15/115 -> 55.304348 | L37: =H37-K37 -> 368.69565 | M37: 36.87 | N37: =L37-M37 -> 331.82565 | P37: 423 | Q37: =P37/G37 -> 35.25 | R37: 8 | S37: =(R37/G37) -> 0.66666667 | T37: =P37*15/115 -> 55.173913 | U37: =P37-T37 -> 367.82609 | V37: 24 | W37: =V37/G37 -> 2 | X37: 76.8 | Y37: =(X37/P37) -> 0.18156028 | AA37: =H37 -> 424 | AB37: =N37 -> 331.82565 | AC37: =P37 -> 423 | AD37: =U37 -> 367.82609 | AE37: =AA37+AC37 -> 847 | AF37: =AB37+AD37 -> 699.65174
B38: 46048 | C38: Monday | D38: 238 | E38: 19 | F38: 1110 | G38: 23 | H38: 736 | I38: =H38/G38 -> 32 | J38: =G38/F38 -> 0.020720721 | K38: =H38*15/115 -> 96 | L38: =H38-K38 -> 640 | M38: 64.01 | N38: =L38-M38 -> 575.99 | P38: 225 | Q38: =P38/G38 -> 9.7826087 | R38: 8 | S38: =(R38/G38) -> 0.34782609 | T38: =P38*15/115 -> 29.347826 | U38: =P38-T38 -> 195.65217 | V38: 12 | W38: =V38/G38 -> 0.52173913 | X38: 50.06 | Y38: =(X38/P38) -> 0.22248889 | AA38: =H38 -> 736 | AB38: =N38 -> 575.99 | AC38: =P38 -> 225 | AD38: =U38 -> 195.65217 | AE38: =AA38+AC38 -> 961 | AF38: =AB38+AD38 -> 771.64217
B39: 46049 | C39: Tuesday | D39: 238 | E39: 19 | F39: 1110 | G39: 10 | H39: 330 | I39: =H39/G39 -> 33 | J39: =G39/F39 -> 0.009009009 | K39: =H39*15/115 -> 43.043478 | L39: =H39-K39 -> 286.95652 | M39: 28.7 | N39: =L39-M39 -> 258.25652 | P39: 354 | Q39: =P39/G39 -> 35.4 | R39: 13 | S39: =(R39/G39) -> 1.3 | T39: =P39*15/115 -> 46.173913 | U39: =P39-T39 -> 307.82609 | V39: 19 | W39: =V39/G39 -> 1.9 | X39: 55.37 | Y39: =(X39/P39) -> 0.15641243 | AA39: =H39 -> 330 | AB39: =N39 -> 258.25652 | AC39: =P39 -> 354 | AD39: =U39 -> 307.82609 | AE39: =AA39+AC39 -> 684 | AF39: =AB39+AD39 -> 566.08261
B40: 46050 | C40: Wednesday | D40: 238 | E40: 19 | F40: 1110 | G40: 21 | H40: 702 | I40: =H40/G40 -> 33.428571 | J40: =G40/F40 -> 0.018918919 | K40: =H40*15/115 -> 91.565217 | L40: =H40-K40 -> 610.43478 | M40: 61.05 | N40: =L40-M40 -> 549.38478 | P40: 471 | Q40: =P40/G40 -> 22.428571 | R40: 17 | S40: =(R40/G40) -> 0.80952381 | T40: =P40*15/115 -> 61.434783 | U40: =P40-T40 -> 409.56522 | V40: 24 | W40: =V40/G40 -> 1.1428571 | X40: 86.21 | Y40: =(X40/P40) -> 0.18303609 | AA40: =H40 -> 702 | AB40: =N40 -> 549.38478 | AC40: =P40 -> 471 | AD40: =U40 -> 409.56522 | AE40: =AA40+AC40 -> 1173 | AF40: =AB40+AD40 -> 958.95
B41: 46051 | C41: Thursday | D41: 238 | E41: 17 | F41: 1016 | G41: 54 | H41: 1738 | I41: =H41/G41 -> 32.185185 | J41: =G41/F41 -> 0.053149606 | K41: =H41*15/115 -> 226.69565 | L41: =H41-K41 -> 1511.3043 | M41: 151.15 | N41: =L41-M41 -> 1360.1543 | P41: 867 | Q41: =P41/G41 -> 16.055556 | R41: 27 | S41: =(R41/G41) -> 0.5 | T41: =P41*15/115 -> 113.08696 | U41: =P41-T41 -> 753.91304 | V41: 46 | W41: =V41/G41 -> 0.85185185 | X41: 169.88 | Y41: =(X41/P41) -> 0.19594002 | AA41: =H41 -> 1738 | AB41: =N41 -> 1360.1543 | AC41: =P41 -> 867 | AD41: =U41 -> 753.91304 | AE41: =AA41+AC41 -> 2605 | AF41: =AB41+AD41 -> 2114.0674
B42: 46052 | C42: Friday | D42: 238 | E42: 16 | F42: 952 | G42: 82 | H42: 2714 | I42: =H42/G42 -> 33.097561 | J42: =G42/F42 -> 0.086134454 | K42: =H42*15/115 -> 354 | L42: =H42-K42 -> 2360 | M42: 236.03 | N42: =L42-M42 -> 2123.97 | P42: 1059 | Q42: =P42/G42 -> 12.914634 | R42: 32 | S42: =(R42/G42) -> 0.3902439 | T42: =P42*15/115 -> 138.13043 | U42: =P42-T42 -> 920.86957 | V42: 52 | W42: =V42/G42 -> 0.63414634 | X42: 199.54 | Y42: =(X42/P42) -> 0.18842304 | AA42: =H42 -> 2714 | AB42: =N42 -> 2123.97 | AC42: =P42 -> 1059 | AD42: =U42 -> 920.86957 | AE42: =AA42+AC42 -> 3773 | AF42: =AB42+AD42 -> 3044.8396
B43: 46053 | C43: Saturday | D43: 238 | E43: 16 | F43: 952 | G43: 29 | H43: 1058 | I43: =H43/G43 -> 36.482759 | J43: =G43/F43 -> 0.030462185 | K43: =H43*15/115 -> 138 | L43: =H43-K43 -> 920 | M43: 92.02 | N43: =L43-M43 -> 827.98 | P43: 780 | Q43: =P43/G43 -> 26.896552 | R43: 21 | S43: =(R43/G43) -> 0.72413793 | T43: =P43*15/115 -> 101.73913 | U43: =P43-T43 -> 678.26087 | V43: 45 | W43: =V43/G43 -> 1.5517241 | X43: 137.91 | Y43: =(X43/P43) -> 0.17680769 | AA43: =H43 -> 1058 | AB43: =N43 -> 827.98 | AC43: =P43 -> 780 | AD43: =U43 -> 678.26087 | AE43: =AA43+AC43 -> 1838 | AF43: =AB43+AD43 -> 1506.2409
B44: TOTAL | D44: =AVERAGE(D13:D43) -> 238 | E44: =SUM(E13:E43) -> 562 | F44: =SUM(F13:F43) -> 33185 | G44: =SUM(G13:G43) -> 1265 | H44: =SUM(H13:H43) -> 42380 | I44: =H44/G44 -> 33.501976 | J44: =(G44/F44) -> 0.038119632 | K44: =SUM(K13:K43) -> 5527.8261 | L44: =SUM(L13:L43) -> 36852.174 | M44: =SUM(M13:M43) -> 3379.13 | N44: =SUM(N13:N43) -> 33473.044 | P44: =SUM(P13:P43) -> 22104 | Q44: =P44/G44 -> 17.473518 | R44: =SUM(R13:R43) -> 670 | S44: =(R44/G44) -> 0.52964427 | T44: =SUM(T13:T43) -> 2883.1304 | U44: =SUM(U13:U43) -> 19220.87 | V44: =SUM(V13:V43) -> 1426 | W44: =V44/G44 -> 1.1272727 | X44: =SUM(X13:X43) -> 4410.68 | Y44: =(X44/P44) -> 0.19954216 | AA44: =SUM(AA13:AA43) -> 42380 | AB44: =SUM(AB13:AB43) -> 33473.044 | AC44: =SUM(AC13:AC43) -> 22104 | AD44: =SUM(AD13:AD43) -> 19220.87 | AE44: =SUM(AE13:AE43) -> 64484 | AF44: =SUM(AF13:AF43) -> 52693.913

Sheet Feb 2026
B2: NOIR Cinemas - Unaizah
B3: Managed & Operated by - Mukta A2 Cinemas
B5: Cinema | D5: Noir Cinema | G5: Month | I5: 46054
B6: Location | D6: Unizah | G6: Financial Year | I6: 2026
B7: Screens | D7: 4 | G7: VAT | I7: 0.15
B8: Seats | D8: 238 | G8: GCAM | I8: 0.1
G10: Box Office | P10: Concession | AA10: Total Box Office Revenue | AC10: Total Concession Revenue | AE10: Grand Total Revenue
B11: Date | C11: Day | D11: Seats | E11: Total Shows | F11: Total Available Capacity | G11: Admits | H11: Box Office Revenue | I11: ATP | J11: Occ % | K11: VAT (15%) | L11: Net BO Rev Before GCAM | M11: GCAM | N11: Net BO Rev After GCAM | P11: Concession Rev | Q11: SPH | R11: Transaction | S11: ASR | T11: VAT | U11: Net Concession Revenue | V11: Items Sold | W11: Concession Conversion % | X11: Concessions Standard Cost | Y11: COGS | AA11: Gross | AB11: Nett | AC11: Gross | AD11: Nett | AE11: Gross | AF11: Nett
B12: TOTAL MTD | D12: =D41 -> 238 | E12: =E41 -> 367 | F12: =F41 -> 21819 | G12: =G41 -> 462 | H12: =H41 -> 12602 | I12: =I41 -> 27.277056 | J12: =J41 -> 0.021174206 | K12: =K41 -> 1643.7391 | ... N12: =N41 -> 9862.3509 | P12: =P41 -> 12145.78 | Q12: =Q41 -> 26.289567 | R12: =R41 -> 372 | S12: =S41 -> 0.80519481 | T12: =T41 -> 1584.2322 | U12: =U41 -> 10561.548 | V12: =V41 -> 711 | W12: =W41 -> 1.538961 | ... Y12: =Y41 -> 0.19152907 | AA12: =AA41 -> 12602 | AB12: =AB41 -> 9862.3509 | AC12: =AC41 -> 12145.78 | AD12: =AD41 -> 10561.548 | AE12: =AE41 -> 24747.78 | AF12: =AF41 -> 20423.899
B13: 46054 | C13: Sunday | D13: 238 | E13: 16 | F13: 952 | G13: 24 | H13: 768 | I13: =H13/G13 -> 32 | J13: =G13/F13 -> 0.025210084 | K13: =H13*15/115 -> 100.17391 | L13: =H13-K13 -> 667.82609 | M13: 66.79 | N13: =L13-M13 -> 601.03609 | P13: 474 | Q13: =P13/G13 -> 19.75 | R13: 17 | S13: =(R13/G13) -> 0.70833333 | T13: =P13*15/115 -> 61.826087 | U13: =P13-T13 -> 412.17391 | V13: 25 | W13: =V13/G13 -> 1.0416667 | X13: 116 | Y13: =(X13/P13) -> 0.24472574 | AA13: =H13 -> 768 | AB13: =N13 -> 601.03609 | AC13: =P13 -> 474 | AD13: =U13 -> 412.17391 | AE13: =AA13+AC13 -> 1242 | AF13: =AB13+AD13 -> 1013.21
B14: 46055 | C14: Monday | D14: 238 | E14: 16 | F14: 952 | G14: 12 | H14: 384 | I14: =H14/G14 -> 32 | J14: =G14/F14 -> 0.012605042 | K14: =H14*15/115 -> 50.086957 | L14: =H14-K14 -> 333.91304 | M14: 33.4 | N14: =L14-M14 -> 300.51304 | P14: 360 | Q14: =P14/G14 -> 30 | R14: 12 | S14: =(R14/G14) -> 1 | T14: =P14*15/115 -> 46.956522 | U14: =P14-T14 -> 313.04348 | V14: 20 | W14: =V14/G14 -> 1.6666667 | X14: 60.67 | Y14: =(X14/P14) -> 0.16852778 | AA14: =H14 -> 384 | AB14: =N14 -> 300.51304 | AC14: =P14 -> 360 | AD14: =U14 -> 313.04348 | AE14: =AA14+AC14 -> 744 | AF14: =AB14+AD14 -> 613.55652
B15: 46056 | C15: Tuesday | D15: 238 | E15: 16 | F15: 952 | G15: 17 | H15: 564 | I15: =H15/G15 -> 33.176471 | J15: =G15/F15 -> 0.017857143 | K15: =H15*15/115 -> 73.565217 | L15: =H15-K15 -> 490.43478 | M15: 49.05 | N15: =L15-M15 -> 441.38478 | P15: 349 | Q15: =P15/G15 -> 20.529412 | R15: 13 | S15: =(R15/G15) -> 0.76470588 | T15: =P15*15/115 -> 45.521739 | U15: =P15-T15 -> 303.47826 | V15: 22 | W15: =V15/G15 -> 1.2941176 | X15: 68.19 | Y15: =(X15/P15) -> 0.19538682 | AA15: =H15 -> 564 | AB15: =N15 -> 441.38478 | AC15: =P15 -> 349 | AD15: =U15 -> 303.47826 | AE15: =AA15+AC15 -> 913 | AF15: =AB15+AD15 -> 744.86304
B16: 46057 | C16: Wednesday | D16: 238 | E16: 16 | F16: 952 | G16: 13 | H16: 446 | I16: =H16/G16 -> 34.307692 | J16: =G16/F16 -> 0.013655462 | K16: =H16*15/115 -> 58.173913 | L16: =H16-K16 -> 387.82609 | M16: 38.79 | N16: =L16-M16 -> 349.03609 | P16: 243 | Q16: =P16/G16 -> 18.692308 | R16: 9 | S16: =(R16/G16) -> 0.69230769 | T16: =P16*15/115 -> 31.695652 | U16: =P16-T16 -> 211.30435 | V16: 14 | W16: =V16/G16 -> 1.0769231 | X16: 36.45 | Y16: =(X16/P16) -> 0.15 | AA16: =H16 -> 446 | AB16: =N16 -> 349.03609 | AC16: =P16 -> 243 | AD16: =U16 -> 211.30435 | AE16: =AA16+AC16 -> 689 | AF16: =AB16+AD16 -> 560.34043
B17: 46058 | C17: Thursday | D17: 238 | E17: 16 | F17: 952 | G17: 45 | H17: 1020 | I17: =H17/G17 -> 22.666667 | J17: =G17/F17 -> 0.047268908 | K17: =H17*15/115 -> 133.04348 | L17: =H17-K17 -> 886.95652 | M17: 88.7 | N17: =L17-M17 -> 798.25652 | P17: 685 | Q17: =P17/G17 -> 15.222222 | R17: 23 | S17: =(R17/G17) -> 0.51111111 | T17: =P17*15/115 -> 89.347826 | U17: =P17-T17 -> 595.65217 | V17: 44 | W17: =V17/G17 -> 0.97777778 | X17: 135.9 | Y17: =(X17/P17) -> 0.19839416 | AA17: =H17 -> 1020 | AB17: =N17 -> 798.25652 | AC17: =P17 -> 685 | AD17: =U17 -> 595.65217 | AE17: =AA17+AC17 -> 1705 | AF17: =AB17+AD17 -> 1393.9087
B18: 46059 | C18: Friday | D18: 238 | E18: 16 | F18: 952 | G18: 95 | H18: 2090 | I18: =H18/G18 -> 22 | J18: =G18/F18 -> 0.099789916 | K18: =H18*15/115 -> 272.6087 | L18: =H18-K18 -> 1817.3913 | M18: 181.74 | N18: =L18-M18 -> 1635.6513 | P18: 1656 | Q18: =P18/G18 -> 17.431579 | R18: 38 | S18: =(R18/G18) -> 0.4 | T18: =P18*15/115 -> 216 | U18: =P18-T18 -> 1440 | V18: 98 | W18: =V18/G18 -> 1.0315789 | X18: 328.62 | Y18: =(X18/P18) -> 0.19844203 | AA18: =H18 -> 2090 | AB18: =N18 -> 1635.6513 | AC18: =P18 -> 1656 | AD18: =U18 -> 1440 | AE18: =AA18+AC18 -> 3746 | AF18: =AB18+AD18 -> 3075.6513
B19: 46060 | C19: Saturday | D19: 238 | E19: 16 | F19: 952 | G19: 30 | H19: 660 | I19: =H19/G19 -> 22 | J19: =G19/F19 -> 0.031512605 | K19: =H19*15/115 -> 86.086957 | L19: =H19-K19 -> 573.91304 | M19: 57.39 | N19: =L19-M19 -> 516.52304 | P19: 869.78 | Q19: =P19/G19 -> 28.992667 | R19: 22 | S19: =(R19/G19) -> 0.73333333 | T19: =P19*15/115 -> 113.44957 | U19: =P19-T19 -> 756.33043 | V19: 42 | W19: =V19/G19 -> 1.4 | X19: 171.69 | Y19: =(X19/P19) -> 0.19739474 | AA19: =H19 -> 660 | AB19: =N19 -> 516.52304 | AC19: =P19 -> 869.78 | AD19: =U19 -> 756.33043 | AE19: =AA19+AC19 -> 1529.78 | AF19: =AB19+AD19 -> 1272.8535
B20: 46061 | C20: Sunday | D20: 238 | E20: 16 | F20: 952 | G20: 20 | H20: 400 | I20: =H20/G20 -> 20 | J20: =G20/F20 -> 0.021008403 | K20: =H20*15/115 -> 52.173913 | L20: =H20-K20 -> 347.82609 | M20: 34.78 | N20: =L20-M20 -> 313.04609 | P20: 300 | Q20: =P20/G20 -> 15 | R20: 8 | S20: =(R20/G20) -> 0.4 | T20: =P20*15/115 -> 39.130435 | U20: =P20-T20 -> 260.86957 | V20: 21 | W20: =V20/G20 -> 1.05 | X20: 63.97 | Y20: =(X20/P20) -> 0.21323333 | AA20: =H20 -> 400 | AB20: =N20 -> 313.04609 | AC20: =P20 -> 300 | AD20: =U20 -> 260.86957 | AE20: =AA20+AC20 -> 700 | AF20: =AB20+AD20 -> 573.91565
B21: 46062 | C21: Monday | D21: 238 | E21: 16 | F21: 952 | G21: 11 | H21: 240 | I21: =H21/G21 -> 21.818182 | J21: =G21/F21 -> 0.011554622 | K21: =H21*15/115 -> 31.304348 | L21: =H21-K21 -> 208.69565 | M21: 20.87 | N21: =L21-M21 -> 187.82565 | P21: 431 | Q21: =P21/G21 -> 39.181818 | R21: 12 | S21: =(R21/G21) -> 1.0909091 | T21: =P21*15/115 -> 56.217391 | U21: =P21-T21 -> 374.78261 | V21: 26 | W21: =V21/G21 -> 2.3636364 | X21: 67.82 | Y21: =(X21/P21) -> 0.15735499 | AA21: =H21 -> 240 | AB21: =N21 -> 187.82565 | AC21: =P21 -> 431 | AD21: =U21 -> 374.78261 | AE21: =AA21+AC21 -> 671 | AF21: =AB21+AD21 -> 562.60826
B22: 46063 | C22: Tuesday | D22: 238 | E22: 16 | F22: 952 | G22: 24 | H22: 520 | I22: =H22/G22 -> 21.666667 | J22: =G22/F22 -> 0.025210084 | K22: =H22*15/115 -> 67.826087 | L22: =H22-K22 -> 452.17391 | M22: 45.22 | N22: =L22-M22 -> 406.95391 | P22: 721 | Q22: =P22/G22 -> 30.041667 | R22: 18 | S22: =(R22/G22) -> 0.75 | T22: =P22*15/115 -> 94.043478 | U22: =P22-T22 -> 626.95652 | V22: 44 | W22: =V22/G22 -> 1.8333333 | X22: 140.86 | Y22: =(X22/P22) -> 0.19536755 | AA22: =H22 -> 520 | AB22: =N22 -> 406.95391 | AC22: =P22 -> 721 | AD22: =U22 -> 626.95652 | AE22: =AA22+AC22 -> 1241 | AF22: =AB22+AD22 -> 1033.9104
B23: 46064 | C23: Wednesday | D23: 238 | E23: 16 | F23: 952 | G23: 11 | H23: 220 | I23: =H23/G23 -> 20 | J23: =G23/F23 -> 0.011554622 | K23: =H23*15/115 -> 28.695652 | L23: =H23-K23 -> 191.30435 | M23: 19.13 | N23: =L23-M23 -> 172.17435 | P23: 367 | Q23: =P23/G23 -> 33.363636 | R23: 12 | S23: =(R23/G23) -> 1.0909091 | T23: =P23*15/115 -> 47.869565 | U23: =P23-T23 -> 319.13043 | V23: 25 | W23: =V23/G23 -> 2.2727273 | X23: 66.06 | Y23: =(X23/P23) -> 0.18 | AA23: =H23 -> 220 | AB23: =N23 -> 172.17435 | AC23: =P23 -> 367 | AD23: =U23 -> 319.13043 | AE23: =AA23+AC23 -> 587 | AF23: =AB23+AD23 -> 491.30478
B24: 46065 | C24: Thursday | D24: 238 | E24: 16 | F24: 952 | G24: 34 | H24: 1108 | I24: =H24/G24 -> 32.588235 | J24: =G24/F24 -> 0.035714286 | K24: =H24*15/115 -> 144.52174 | L24: =H24-K24 -> 963.47826 | M24: 96.36 | N24: =L24-M24 -> 867.11826 | P24: 946 | Q24: =P24/G24 -> 27.823529 | R24: 25 | S24: =(R24/G24) -> 0.73529412 | T24: =P24*15/115 -> 123.3913 | U24: =P24-T24 -> 822.6087 | V24: 54 | W24: =V24/G24 -> 1.5882353 | X24: 183.37 | Y24: =(X24/P24) -> 0.19383721 | AA24: =H24 -> 1108 | AB24: =N24 -> 867.11826 | AC24: =P24 -> 946 | AD24: =U24 -> 822.6087 | AE24: =AA24+AC24 -> 2054 | AF24: =AB24+AD24 -> 1689.727
... B40: 46081 | C40: Saturday | D40: 238 | E40: 8 | F40: 476 | G40: 0 | H40: 0 | I40: =H40/G40 -> #DIV/0! | J40: =G40/F40 -> 0 | K40: =H40*15/115 -> 0 | L40: =H40-K40 -> 0 | M40: 0 | N40: =L40-M40 -> 0 | P40: 164 | Q40: =P40/G40 -> #DIV/0! | R40: 5 | S40: =(R40/G40) -> #DIV/0! | T40: =P40*15/115 -> 21.391304 | U40: =P40-T40 -> 142.6087 | V40: 10 | W40: =V40/G40 -> #DIV/0! | X40: 34.52 | Y40: =(X40/P40) -> 0.2104878 | AA40: =H40 -> 0 | AB40: =N40 -> 0 | AC40: =P40 -> 164 | AD40: =U40 -> 142.6087 | AE40: =AA40+AC40 -> 164 | AF40: =AB40+AD40 -> 142.6087
B41: TOTAL | D41: =AVERAGE(D13:D40) -> 238 | E41: =SUM(E13:E40) -> 367 | F41: =SUM(F13:F40) -> 21819 | G41: =SUM(G13:G40) -> 462 | H41: =SUM(H13:H40) -> 12602 | I41: =H41/G41 -> 27.277056 | J41: =(G41/F41) -> 0.021174206 | K41: =SUM(K13:K40) -> 1643.7391 | L41: =SUM(L13:L40) -> 10958.261 | M41: =SUM(M13:M40) -> 1095.91 | N41: =SUM(N13:N40) -> 9862.3509 | P41: =SUM(P13:P40) -> 12145.78 | Q41: =P41/G41 -> 26.289567 | R41: =SUM(R13:R40) -> 372 | S41: =(R41/G41) -> 0.80519481 | T41: =SUM(T13:T40) -> 1584.2322 | U41: =SUM(U13:U40) -> 10561.548 | V41: =SUM(V13:V40) -> 711 | W41: =V41/G41 -> 1.538961 | X41: =SUM(X13:X40) -> 2326.27 | Y41: =(X41/P41) -> 0.19152907 | AA41: =SUM(AA13:AA40) -> 12602 | AB41: =SUM(AB13:AB40) -> 9862.3509 | AC41: =SUM(AC13:AC40) -> 12145.78 | AD41: =SUM(AD13:AD40) -> 10561.548 | AE41: =SUM(AE13:AE40) -> 24747.78 | AF41: =SUM(AF13:AF40) -> 20423.899

Sheet Mar2026
B2: NOIR Cinemas - Unaizah
B3: Managed & Operated by - Mukta A2 Cinemas
B5: Cinema | D5: Noir Cinema | G5: Month | I5: 46082
B6: Location | D6: Unizah | G6: Financial Year | I6: 2026
B7: Screens | D7: 4 | G7: VAT | I7: 0.15
B8: Seats | D8: 238 | G8: GCAM | I8: 0.1
G10: Box Office | P10: Concession | AA10: Total Box Office Revenue | AC10: Total Concession Revenue | AE10: Grand Total Revenue
B11: Date | C11: Day | D11: Seats | E11: Total Shows | F11: Total Available Capacity | G11: Admits | H11: Box Office Revenue | I11: ATP | J11: Occ % | K11: VAT (15%) | L11: Net BO Rev Before GCAM | M11: GCAM | N11: Net BO Rev After GCAM | P11: Concession Rev | Q11: SPH | R11: Transaction | S11: ASR | T11: VAT | U11: Net Concession Revenue | V11: Items Sold | W11: Concession Conversion % | X11: Concessions Standard Cost | Y11: COGS | AA11: Gross | AB11: Nett | AC11: Gross | AD11: Nett | AE11: Gross | AF11: Nett
B12: TOTAL MTD | D12: =D44 -> 238 | E12: =E44 -> 411 | F12: =F44 -> 24506 | G12: =G44 -> 3809 | H12: =H44 -> 128578 | I12: =I44 -> 33.756367 | J12: =J44 -> 0.15543132 | K12: =K44 -> 16771.043 | ... N12: =N44 -> 107342.18 | P12: =P44 -> 68528 | Q12: =Q44 -> 17.991074 | R12: =R44 -> 1544 | S12: =S44 -> 0.40535574 | T12: =T44 -> 8938.4348 | U12: =U44 -> 59589.565 | V12: =V44 -> 3553 | W12: =W44 -> 0.93279076 | ... Y12: =Y44 -> 0.18068235 | AA12: =AA44 -> 128578 | AB12: =AB44 -> 107342.18 | AC12: =AC44 -> 68528 | AD12: =AD44 -> 59589.565 | AE12: =AE44 -> 197106 | AF12: =AF44 -> 166931.74
B13: 46082 | C13: Sunday | D13: 238 | E13: 8 | F13: 476 | G13: 6 | H13: 192 | I13: =H13/G13 -> 32 | J13: =G13/F13 -> 0.012605042 | K13: =H13*15/115 -> 25.043478 | L13: =H13-K13 -> 166.95652 | M13: 16.7 | N13: =L13-M13 -> 150.25652 | P13: 466 | Q13: =P13/G13 -> 77.666667 | R13: 17 | S13: =(R13/G13) -> 2.8333333 | T13: =P13*15/115 -> 60.782609 | U13: =P13-T13 -> 405.21739 | V13: 33 | W13: =V13/G13 -> 5.5 | X13: 71.3 | Y13: =(X13/P13) -> 0.15300429 | AA13: =H13 -> 192 | AB13: =N13 -> 150.25652 | AC13: =P13 -> 466 | AD13: =U13 -> 405.21739 | AE13: =AA13+AC13 -> 658 | AF13: =AB13+AD13 -> 555.47391
B14: 46083 | C14: Monday | D14: 238 | E14: 8 | F14: 476 | G14: 2 | H14: 64 | I14: =H14/G14 -> 32 | J14: =G14/F14 -> 0.0042016807 | K14: =H14*15/115 -> 8.3478261 | L14: =H14-K14 -> 55.652174 | M14: 5.57 | N14: =L14-M14 -> 50.082174 | P14: 260 | Q14: =P14/G14 -> 130 | R14: 11 | S14: =(R14/G14) -> 5.5 | T14: =P14*15/115 -> 33.913043 | U14: =P14-T14 -> 226.08696 | V14: 16 | W14: =V14/G14 -> 8 | X14: 47.43 | Y14: =(X14/P14) -> 0.18242308 | AA14: =H14 -> 64 | AB14: =N14 -> 50.082174 | AC14: =P14 -> 260 | AD14: =U14 -> 226.08696 | AE14: =AA14+AC14 -> 324 | AF14: =AB14+AD14 -> 276.16913
B15: 46084 | C15: Saturday | D15: 238 | E15: 8 | F15: 476 | G15: 1 | H15: 32 | I15: =H15/G15 -> 32 | J15: =G15/F15 -> 0.0021008403 | K15: =H15*15/115 -> 4.173913 | L15: =H15-K15 -> 27.826087 | M15: 2.78 | N15: =L15-M15 -> 25.046087 | P15: 443 | Q15: =P15/G15 -> 443 | R15: 18 | S15: =(R15/G15) -> 18 | T15: =P15*15/115 -> 57.782609 | U15: =P15-T15 -> 385.21739 | V15: 34 | W15: =V15/G15 -> 34 | X15: 74.21 | Y15: =(X15/P15) -> 0.16751693 | AA15: =H15 -> 32 | AB15: =N15 -> 25.046087 | AC15: =P15 -> 443 | AD15: =U15 -> 385.21739 | AE15: =AA15+AC15 -> 475 | AF15: =AB15+AD15 -> 410.26348
B16: 46085 | C16: Wednesday | D16: 238 | E16: 8 | F16: 476 | G16: 0 | H16: 0 | I16: =H16/G16 -> #DIV/0! | J16: =G16/F16 -> 0 | K16: =H16*15/115 -> 0 | L16: =H16-K16 -> 0 | M16: 0 | N16: =L16-M16 -> 0 | P16: 750 | Q16: =P16/G16 -> #DIV/0! | R16: 21 | S16: =(R16/G16) -> #DIV/0! | T16: =P16*15/115 -> 97.826087 | U16: =P16-T16 -> 652.17391 | V16: 45 | W16: =V16/G16 -> #DIV/0! | X16: 120.75 | Y16: =(X16/P16) -> 0.161 | AA16: =H16 -> 0 | AB16: =N16 -> 0 | AC16: =P16 -> 750 | AD16: =U16 -> 652.17391 | AE16: =AA16+AC16 -> 750 | AF16: =AB16+AD16 -> 652.17391
B17: 46086 | C17: Thursday | D17: 238 | E17: 8 | F17: 476 | G17: 14 | H17: 448 | I17: =H17/G17 -> 32 | J17: =G17/F17 -> 0.029411765 | K17: =H17*15/115 -> 58.434783 | L17: =H17-K17 -> 389.56522 | M17: 38.96 | N17: =L17-M17 -> 350.60522 | P17: 875 | Q17: =P17/G17 -> 62.5 | R17: 27 | S17: =(R17/G17) -> 1.9285714 | T17: =P17*15/115 -> 114.13043 | U17: =P17-T17 -> 760.86957 | V17: 45 | W17: =V17/G17 -> 3.2142857 | X17: 128.88 | Y17: =(X17/P17) -> 0.14729143 | AA17: =H17 -> 448 | AB17: =N17 -> 350.60522 | AC17: =P17 -> 875 | AD17: =U17 -> 760.86957 | AE17: =AA17+AC17 -> 1323 | AF17: =AB17+AD17 -> 1111.4748
B18: 46087 | C18: Friday | D18: 238 | E18: 8 | F18: 476 | G18: 16 | H18: 532 | I18: =H18/G18 -> 33.25 | J18: =G18/F18 -> 0.033613445 | K18: =H18*15/115 -> 69.391304 | L18: =H18-K18 -> 462.6087 | M18: 46.27 | N18: =L18-M18 -> 416.3387 | P18: 733 | Q18: =P18/G18 -> 45.8125 | R18: 26 | S18: =(R18/G18) -> 1.625 | T18: =P18*15/115 -> 95.608696 | U18: =P18-T18 -> 637.3913 | V18: 41 | W18: =V18/G18 -> 2.5625 | X18: 126.65 | Y18: =(X18/P18) -> 0.17278308 | AA18: =H18 -> 532 | AB18: =N18 -> 416.3387 | AC18: =P18 -> 733 | AD18: =U18 -> 637.3913 | AE18: =AA18+AC18 -> 1265 | AF18: =AB18+AD18 -> 1053.73
B19: 46088 | C19: Saturday | D19: 238 | E19: 8 | F19: 476 | G19: 3 | H19: 126 | I19: =H19/G19 -> 42 | J19: =G19/F19 -> 0.006302521 | K19: =H19*15/115 -> 16.434783 | L19: =H19-K19 -> 109.56522 | M19: 10.96 | N19: =L19-M19 -> 98.605217 | P19: 813 | Q19: =P19/G19 -> 271 | R19: 30 | S19: =(R19/G19) -> 10 | T19: =P19*15/115 -> 106.04348 | U19: =P19-T19 -> 706.95652 | V19: 43 | W19: =V19/G19 -> 14.333333 | X19: 147.94 | Y19: =(X19/P19) -> 0.18196802 | AA19: =H19 -> 126 | AB19: =N19 -> 98.605217 | AC19: =P19 -> 813 | AD19: =U19 -> 706.95652 | AE19: =AA19+AC19 -> 939 | AF19: =AB19+AD19 -> 805.56174
B20: 46089 | C20: Sunday | D20: 238 | E20: 8 | F20: 476 | G20: 1 | H20: 32 | I20: =H20/G20 -> 32 | J20: =G20/F20 -> 0.0021008403 | K20: =H20*15/115 -> 4.173913 | L20: =H20-K20 -> 27.826087 | M20: 2.78 | N20: =L20-M20 -> 25.046087 | P20: 787 | Q20: =P20/G20 -> 787 | R20: 22 | S20: =(R20/G20) -> 22 | T20: =P20*15/115 -> 102.65217 | U20: =P20-T20 -> 684.34783 | V20: 46 | W20: =V20/G20 -> 46 | X20: 144.88 | Y20: =(X20/P20) -> 0.18409149 | AA20: =H20 -> 32 | AB20: =N20 -> 25.046087 | AC20: =P20 -> 787 | AD20: =U20 -> 684.34783 | AE20: =AA20+AC20 -> 819 | AF20: =AB20+AD20 -> 709.39391
B21: 46090 | C21: Monday | D21: 238 | E21: 8 | F21: 476 | G21: 1 | H21: 32 | I21: =H21/G21 -> 32 | J21: =G21/F21 -> 0.0021008403 | K21: =H21*15/115 -> 4.173913 | L21: =H21-K21 -> 27.826087 | M21: 2.78 | N21: =L21-M21 -> 25.046087 | P21: 544 | Q21: =P21/G21 -> 544 | R21: 20 | S21: =(R21/G21) -> 20 | T21: =P21*15/115 -> 70.956522 | U21: =P21-T21 -> 473.04348 | V21: 29 | W21: =V21/G21 -> 29 | X21: 86.5 | Y21: =(X21/P21) -> 0.15900735 | AA21: =H21 -> 32 | AB21: =N21 -> 25.046087 | AC21: =P21 -> 544 | AD21: =U21 -> 473.04348 | AE21: =AA21+AC21 -> 576 | AF21: =AB21+AD21 -> 498.08957
B22: 46091 | C22: Tuesday | D22: 238 | E22: 8 | F22: 476 | G22: 2 | H22: 84 | I22: =H22/G22 -> 42 | J22: =G22/F22 -> 0.0042016807 | K22: =H22*15/115 -> 10.956522 | L22: =H22-K22 -> 73.043478 | M22: 7.3 | N22: =L22-M22 -> 65.743478 | P22: 576 | Q22: =P22/G22 -> 288 | R22: 25 | S22: =(R22/G22) -> 12.5 | T22: =P22*15/115 -> 75.130435 | U22: =P22-T22 -> 500.86957 | V22: 31 | W22: =V22/G22 -> 15.5 | X22: 99.71 | Y22: =(X22/P22) -> 0.17310764 | AA22: =H22 -> 84 | AB22: =N22 -> 65.743478 | AC22: =P22 -> 576 | AD22: =U22 -> 500.86957 | AE22: =AA22+AC22 -> 660 | AF22: =AB22+AD22 -> 566.61304
B23: 46092 | C23: Wednesday | D23: 238 | E23: 8 | F23: 476 | G23: 1 | H23: 32 | I23: =H23/G23 -> 32 | J23: =G23/F23 -> 0.0021008403 | K23: =H23*15/115 -> 4.173913 | L23: =H23-K23 -> 27.826087 | M23: 2.78 | N23: =L23-M23 -> 25.046087 | P23: 362 | Q23: =P23/G23 -> 362 | R23: 14 | S23: =(R23/G23) -> 14 | T23: =P23*15/115 -> 47.217391 | U23: =P23-T23 -> 314.78261 | V23: 23 | W23: =V23/G23 -> 23 | X23: 58.84 | Y23: =(X23/P23) -> 0.16254144 | AA23: =H23 -> 32 | AB23: =N23 -> 25.046087 | AC23: =P23 -> 362 | AD23: =U23 -> 314.78261 | AE23: =AA23+AC23 -> 394 | AF23: =AB23+AD23 -> 339.8287
B24: 46093 | C24: Thursday | D24: 238 | E24: 8 | F24: 476 | G24: 0 | H24: 0 | I24: =H24/G24 -> #DIV/0! | J24: =G24/F24 -> 0 | K24: =H24*15/115 -> 0 | L24: =H24-K24 -> 0 | M24: 0 | N24: =L24-M24 -> 0 | P24: 448 | Q24: =P24/G24 -> #DIV/0! | R24: 18 | S24: =(R24/G24) -> #DIV/0! | T24: =P24*15/115 -> 58.434783 | U24: =P24-T24 -> 389.56522 | V24: 31 | W24: =V24/G24 -> #DIV/0! | X24: 65.9 | Y24: =(X24/P24) -> 0.14709821 | AA24: =H24 -> 0 | AB24: =N24 -> 0 | AC24: =P24 -> 448 | AD24: =U24 -> 389.56522 | AE24: =AA24+AC24 -> 448 | AF24: =AB24+AD24 -> 389.56522
... B43: 46112 | C43: Tuesday | D43: 238 | E43: 16 | F43: 948 | G43: 45 | H43: 1440 | I43: =H43/G43 -> 32 | J43: =G43/F43 -> 0.047468354 | K43: =H43*15/115 -> 187.82609 | L43: =H43-K43 -> 1252.1739 | M43: 47.31 | N43: =L43-M43 -> 1204.8639 | P43: 621 | Q43: =P43/G43 -> 13.8 | R43: 16 | S43: =(R43/G43) -> 0.35555556 | T43: =P43*15/115 -> 81 | U43: =P43-T43 -> 540 | V43: 36 | W43: =V43/G43 -> 0.8 | X43: 95.98 | Y43: =(X43/P43) -> 0.15455717 | AA43: =H43 -> 1440 | AB43: =N43 -> 1204.8639 | AC43: =P43 -> 621 | AD43: =U43 -> 540 | AE43: =AA43+AC43 -> 2061 | AF43: =AB43+AD43 -> 1744.8639
B44: TOTAL | D44: =AVERAGE(D13:D43) -> 238 | E44: =SUM(E13:E43) -> 411 | F44: =SUM(F13:F43) -> 24506 | G44: =SUM(G13:G43) -> 3809 | H44: =SUM(H13:H43) -> 128578 | I44: =H44/G44 -> 33.756367 | J44: =(G44/F44) -> 0.15543132 | K44: =SUM(K13:K43) -> 16771.043 | L44: =SUM(L13:L43) -> 111806.96 | M44: =SUM(M13:M43) -> 4464.78 | N44: =SUM(N13:N43) -> 107342.18 | P44: =SUM(P13:P43) -> 68528 | Q44: =P44/G44 -> 17.991074 | R44: =SUM(R13:R43) -> 1544 | S44: =(R44/G44) -> 0.40535574 | T44: =SUM(T13:T43) -> 8938.4348 | U44: =SUM(U13:U43) -> 59589.565 | V44: =SUM(V13:V43) -> 3553 | W44: =V44/G44 -> 0.93279076 | X44: =SUM(X13:X43) -> 12381.8 | Y44: =(X44/P44) -> 0.18068235 | AA44: =SUM(AA13:AA43) -> 128578 | AB44: =SUM(AB13:AB43) -> 107342.18 | AC44: =SUM(AC13:AC43) -> 68528 | AD44: =SUM(AD13:AD43) -> 59589.565 | AE44: =SUM(AE13:AE43) -> 197106 | AF44: =SUM(AF13:AF43) -> 166931.74

Sheet Apr2026
B2: NOIR Cinemas - Unaizah
B3: Managed & Operated by - Mukta A2 Cinemas
B5: Cinema | D5: Noir Cinema | G5: Month | I5: 46113
B6: Location | D6: Unizah | G6: Financial Year | I6: 2026
B7: Screens | D7: 4 | G7: VAT | I7: 0.15
B8: Seats | D8: 238 | G8: GCAM | I8: 0.1
G10: Box Office | P10: Concession | AA10: Total Box Office Revenue | AC10: Total Concession Revenue | AE10: Grand Total Revenue
B11: Date | C11: Day | D11: Seats | E11: Total Shows | F11: Total Available Capacity | G11: Admits | H11: Box Office Revenue | I11: ATP | J11: Occ % | K11: VAT (15%) | L11: Net BO Rev Before GCAM | M11: GCAM | N11: Net BO Rev After GCAM | P11: Concession Rev | Q11: SPH | R11: Transaction | S11: ASR | T11: VAT | U11: Net Concession Revenue | V11: Items Sold | W11: Concession Conversion % | X11: Concessions Standard Cost | Y11: COGS | AA11: Gross | AB11: Nett | AC11: Gross | AD11: Nett | AE11: Gross | AF11: Nett
B12: TOTAL MTD | D12: =D44 -> 238 | E12: =E44 -> 582 | F12: =F44 -> 34619 | G12: =G44 -> 3689 | H12: =H44 -> 123506.8 | I12: =I44 -> 33.479751 | J12: =J44 -> 0.10655998 | K12: =K44 -> 16109.583 | ... N12: =N44 -> 100374.97 | P12: =P44 -> 50049.53 | Q12: =Q44 -> 13.567235 | R12: =R44 -> 1187 | S12: =S44 -> 0.32176742 | T12: =T44 -> 6528.1996 | U12: =U44 -> 43521.33 | V12: =V44 -> 2611 | W12: =W44 -> 0.70777989 | ... Y12: =Y44 -> 0.17203418 | AA12: =AA44 -> 123506.8 | AB12: =AB44 -> 100374.97 | AC12: =AC44 -> 50049.53 | AD12: =AD44 -> 43521.33 | AE12: =AE44 -> 173556.33 | AF12: =AF44 -> 143896.3
B13: 46113 | C13: Wednesday | D13: 238 | E13: 17 | F13: 1012 | G13: 120 | H13: 4060 | I13: =H13/G13 -> 33.833333 | J13: =G13/F13 -> 0.11857708 | K13: =H13*15/115 -> 529.56522 | L13: =H13-K13 -> 3530.4348 | M13: 116.88 | N13: =L13-M13 -> 3413.5548 | P13: 2137 | Q13: =P13/G13 -> 17.808333 | R13: 40 | S13: =(R13/G13) -> 0.33333333 | T13: =P13*15/115 -> 278.73913 | U13: =P13-T13 -> 1858.2609 | V13: 119 | W13: =V13/G13 -> 0.99166667 | X13: 381.06 | Y13: =(X13/P13) -> 0.1783154 | AA13: =H13 -> 4060 | AB13: =N13 -> 3413.5548 | AC13: =P13 -> 2137 | AD13: =U13 -> 1858.2609 | AE13: =AA13+AC13 -> 6197 | AF13: =AB13+AD13 -> 5271.8157
B14: 46114 | C14: Thursday | D14: 238 | E14: 21 | F14: 1234 | G14: 294 | H14: 9748 | I14: =H14/G14 -> 33.156463 | J14: =G14/F14 -> 0.23824959 | K14: =H14*15/115 -> 1271.4783 | L14: =H14-K14 -> 8476.5217 | M14: 351.34 | N14: =L14-M14 -> 8125.1817 | P14: 3480 | Q14: =P14/G14 -> 11.836735 | R14: 76 | S14: =(R14/G14) -> 0.2585034 | T14: =P14*15/115 -> 453.91304 | U14: =P14-T14 -> 3026.087 | V14: 176 | W14: =V14/G14 -> 0.59863946 | X14: 547.89 | Y14: =(X14/P14) -> 0.15743966 | AA14: =H14 -> 9748 | AB14: =N14 -> 8125.1817 | AC14: =P14 -> 3480 | AD14: =U14 -> 3026.087 | AE14: =AA14+AC14 -> 13228 | AF14: =AB14+AD14 -> 11151.269
B15: 46115 | C15: Friday | D15: 238 | E15: 22 | F15: 1298 | G15: 445 | H15: 14870 | I15: =H15/G15 -> 33.41573 | J15: =G15/F15 -> 0.34283513 | K15: =H15*15/115 -> 1939.5652 | L15: =H15-K15 -> 12930.435 | M15: 670.51 | N15: =L15-M15 -> 12259.925 | P15: 6259 | Q15: =P15/G15 -> 14.065169 | R15: 107 | S15: =(R15/G15) -> 0.24044944 | T15: =P15*15/115 -> 816.3913 | U15: =P15-T15 -> 5442.6087 | V15: 317 | W15: =V15/G15 -> 0.71235955 | X15: 1018.33 | Y15: =(X15/P15) -> 0.16269851 | AA15: =H15 -> 14870 | AB15: =N15 -> 12259.925 | AC15: =P15 -> 6259 | AD15: =U15 -> 5442.6087 | AE15: =AA15+AC15 -> 21129 | AF15: =AB15+AD15 -> 17702.533
B16: 46116 | C16: Saturday | D16: 238 | E16: 25 | F16: 1472 | G16: 253 | H16: 8516 | I16: =H16/G16 -> 33.660079 | J16: =G16/F16 -> 0.171875 | K16: =H16*15/115 -> 1110.7826 | L16: =H16-K16 -> 7405.2174 | M16: 501.7 | N16: =L16-M16 -> 6903.5174 | P16: 3268 | Q16: =P16/G16 -> 12.916996 | R16: 77 | S16: =(R16/G16) -> 0.30434783 | T16: =P16*15/115 -> 426.26087 | U16: =P16-T16 -> 2841.7391 | V16: 161 | W16: =V16/G16 -> 0.63636364 | X16: 552.6 | Y16: =(X16/P16) -> 0.16909425 | AA16: =H16 -> 8516 | AB16: =N16 -> 6903.5174 | AC16: =P16 -> 3268 | AD16: =U16 -> 2841.7391 | AE16: =AA16+AC16 -> 11784 | AF16: =AB16+AD16 -> 9745.2565
B17: 46117 | C17: Sunday | D17: 238 | E17: 19 | F17: 1133 | G17: 171 | H17: 5702 | I17: =H17/G17 -> 33.345029 | J17: =G17/F17 -> 0.15092674 | K17: =H17*15/115 -> 743.73913 | L17: =H17-K17 -> 4958.2609 | M17: 426.31 | N17: =L17-M17 -> 4531.9509 | P17: 1368.93 | Q17: =P17/G17 -> 8.0054386 | R17: 40 | S17: =(R17/G17) -> 0.23391813 | T17: =P17*15/115 -> 178.55609 | U17: =P17-T17 -> 1190.3739 | V17: 78 | W17: =V17/G17 -> 0.45614035 | X17: 279.73 | Y17: =(X17/P17) -> 0.20434208 | AA17: =H17 -> 5702 | AB17: =N17 -> 4531.9509 | AC17: =P17 -> 1368.93 | AD17: =U17 -> 1190.3739 | AE17: =AA17+AC17 -> 7070.93 | AF17: =AB17+AD17 -> 5722.3248
B18: 46118 | C18: Monday | D18: 238 | E18: 20 | F18: 1197 | G18: 186 | H18: 6212 | I18: =H18/G18 -> 33.397849 | J18: =G18/F18 -> 0.15538847 | K18: =H18*15/115 -> 810.26087 | L18: =H18-K18 -> 5401.7391 | M18: 515.19 | N18: =L18-M18 -> 4886.5491 | P18: 1347 | Q18: =P18/G18 -> 7.2419355 | R18: 44 | S18: =(R18/G18) -> 0.23655914 | T18: =P18*15/115 -> 175.69565 | U18: =P18-T18 -> 1171.3043 | V18: 69 | W18: =V18/G18 -> 0.37096774 | X18: 239.67 | Y18: =(X18/P18) -> 0.17792873 | AA18: =H18 -> 6212 | AB18: =N18 -> 4886.5491 | AC18: =P18 -> 1347 | AD18: =U18 -> 1171.3043 | AE18: =AA18+AC18 -> 7559 | AF18: =AB18+AD18 -> 6057.8535
B19: 46119 | C19: Tuesday | D19: 238 | E19: 19 | F19: 1133 | G19: 145 | H19: 4820 | I19: =H19/G19 -> 33.241379 | J19: =G19/F19 -> 0.12797882 | K19: =H19*15/115 -> 628.69565 | L19: =H19-K19 -> 4191.3043 | M19: 330.12 | N19: =L19-M19 -> 3861.1843 | P19: 1764 | Q19: =P19/G19 -> 12.165517 | R19: 44 | S19: =(R19/G19) -> 0.30344828 | T19: =P19*15/115 -> 230.08696 | U19: =P19-T19 -> 1533.913 | V19: 86 | W19: =V19/G19 -> 0.59310345 | X19: 269.27 | Y19: =(X19/P19) -> 0.15264739 | AA19: =H19 -> 4820 | AB19: =N19 -> 3861.1843 | AC19: =P19 -> 1764 | AD19: =U19 -> 1533.913 | AE19: =AA19+AC19 -> 6584 | AF19: =AB19+AD19 -> 5395.0974
B20: 46120 | C20: Wednesday | D20: 238 | E20: 19 | F20: 1133 | G20: 130 | H20: 4360 | I20: =H20/G20 -> 33.538462 | J20: =G20/F20 -> 0.11473963 | K20: =H20*15/115 -> 568.69565 | L20: =H20-K20 -> 3791.3043 | M20: 323.51 | N20: =L20-M20 -> 3467.7943 | P20: 1452 | Q20: =P20/G20 -> 11.169231 | R20: 37 | S20: =(R20/G20) -> 0.28461538 | T20: =P20*15/115 -> 189.3913 | U20: =P20-T20 -> 1262.6087 | V20: 77 | W20: =V20/G20 -> 0.59230769 | X20: 273.94 | Y20: =(X20/P20) -> 0.18866391 | AA20: =H20 -> 4360 | AB20: =N20 -> 3467.7943 | AC20: =P20 -> 1452 | AD20: =U20 -> 1262.6087 | AE20: =AA20+AC20 -> 5812 | AF20: =AB20+AD20 -> 4730.403
B21: 46121 | C21: Thursday | D21: 238 | E21: 20 | F21: 1170 | G21: 306 | H21: 10342 | I21: =H21/G21 -> 33.797386 | J21: =G21/F21 -> 0.26153846 | K21: =H21*15/115 -> 1348.9565 | L21: =H21-K21 -> 8993.0435 | M21: 586.66 | N21: =L21-M21 -> 8406.3835 | P21: 3742 | Q21: =P21/G21 -> 12.228758 | R21: 86 | S21: =(R21/G21) -> 0.28104575 | T21: =P21*15/115 -> 488.08696 | U21: =P21-T21 -> 3253.913 | V21: 191 | W21: =V21/G21 -> 0.62418301 | X21: 661.68 | Y21: =(X21/P21) -> 0.17682523 | AA21: =H21 -> 10342 | AB21: =N21 -> 8406.3835 | AC21: =P21 -> 3742 | AD21: =U21 -> 3253.913 | AE21: =AA21+AC21 -> 14084 | AF21: =AB21+AD21 -> 11660.297
B22: 46122 | C22: Friday | D22: 238 | E22: 19 | F22: 1106 | G22: 437 | H22: 14654 | I22: =H22/G22 -> 33.533181 | J22: =G22/F22 -> 0.39511754 | K22: =H22*15/115 -> 1911.3913 | L22: =H22-K22 -> 12742.609 | M22: 823.56 | N22: =L22-M22 -> 11919.049 | P22: 4449 | Q22: =P22/G22 -> 10.180778 | R22: 118 | S22: =(R22/G22) -> 0.27002288 | T22: =P22*15/115 -> 580.30435 | U22: =P22-T22 -> 3868.6957 | V22: 224 | W22: =V22/G22 -> 0.51258581 | X22: 758 | Y22: =(X22/P22) -> 0.17037537 | AA22: =H22 -> 14654 | AB22: =N22 -> 11919.049 | AC22: =P22 -> 4449 | AD22: =U22 -> 3868.6957 | AE22: =AA22+AC22 -> 19103 | AF22: =AB22+AD22 -> 15787.744
B23: 46123 | C23: Saturday | D23: 238 | E23: 22 | F23: 1280 | G23: 159 | H23: 5358 | I23: =H23/G23 -> 33.698113 | J23: =G23/F23 -> 0.12421875 | K23: =H23*15/115 -> 698.86957 | L23: =H23-K23 -> 4659.1304 | M23: 275.33 | N23: =L23-M23 -> 4383.8004 | P23: 3275 | Q23: =P23/G23 -> 20.597484 | R23: 60 | S23: =(R23/G23) -> 0.37735849 | T23: =P23*15/115 -> 427.17391 | U23: =P23-T23 -> 2847.8261 | V23: 155 | W23: =V23/G23 -> 0.97484277 | X23: 526.54 | Y23: =(X23/P23) -> 0.16077557 | AA23: =H23 -> 5358 | AB23: =N23 -> 4383.8004 | AC23: =P23 -> 3275 | AD23: =U23 -> 2847.8261 | AE23: =AA23+AC23 -> 8633 | AF23: =AB23+AD23 -> 7231.6265
B24: 46124 | C24: Sunday | D24: 238 | E24: 19 | F24: 1106 | G24: 35 | H24: 1200 | I24: =H24/G24 -> 34.285714 | J24: =G24/F24 -> 0.03164557 | K24: =H24*15/115 -> 156.52174 | L24: =H24-K24 -> 1043.4783 | M24: 79.31 | N24: =L24-M24 -> 964.16826 | P24: 753 | Q24: =P24/G24 -> 21.514286 | R24: 24 | S24: =(R24/G24) -> 0.68571429 | T24: =P24*15/115 -> 98.217391 | U24: =P24-T24 -> 654.78261 | V24: 38 | W24: =V24/G24 -> 1.0857143 | X24: 116.66 | Y24: =(X24/P24) -> 0.15492696 | AA24: =H24 -> 1200 | AB24: =N24 -> 964.16826 | AC24: =P24 -> 753 | AD24: =U24 -> 654.78261 | AE24: =AA24+AC24 -> 1953 | AF24: =AB24+AD24 -> 1618.9509
... B43: 46112 | C43: Tuesday | D43: 238 | E43: 0 | F43: 0 | G43: 0 | H43: 0 | I43: =H43/G43 -> #DIV/0! | J43: =G43/F43 -> #DIV/0! | K43: =H43*15/115 -> 0 | L43: =H43-K43 -> 0 | M43: 0 | N43: =L43-M43 -> 0 | P43: 0 | Q43: =P43/G43 -> #DIV/0! | R43: 0 | S43: =(R43/G43) -> #DIV/0! | T43: =P43*15/115 -> 0 | U43: =P43-T43 -> 0 | V43: 0 | W43: =V43/G43 -> #DIV/0! | X43: 0 | Y43: =(X43/P43) -> #DIV/0! | AA43: =H43 -> 0 | AB43: =N43 -> 0 | AC43: =P43 -> 0 | AD43: =U43 -> 0 | AE43: =AA43+AC43 -> 0 | AF43: =AB43+AD43 -> 0
B44: TOTAL | D44: =AVERAGE(D13:D43) -> 238 | E44: =SUM(E13:E43) -> 582 | F44: =SUM(F13:F43) -> 34619 | G44: =SUM(G13:G43) -> 3689 | H44: =SUM(H13:H43) -> 123506.8 | I44: =H44/G44 -> 33.479751 | J44: =(G44/F44) -> 0.10655998 | K44: =SUM(K13:K43) -> 16109.583 | L44: =SUM(L13:L43) -> 107397.22 | M44: =SUM(M13:M43) -> 7022.25 | N44: =SUM(N13:N43) -> 100374.97 | P44: =SUM(P13:P43) -> 50049.53 | Q44: =P44/G44 -> 13.567235 | R44: =SUM(R13:R43) -> 1187 | S44: =(R44/G44) -> 0.32176742 | T44: =SUM(T13:T43) -> 6528.1996 | U44: =SUM(U13:U43) -> 43521.33 | V44: =SUM(V13:V43) -> 2611 | W44: =V44/G44 -> 0.70777989 | X44: =SUM(X13:X43) -> 8610.23 | Y44: =(X44/P44) -> 0.17203418 | AA44: =SUM(AA13:AA43) -> 123506.8 | AB44: =SUM(AB13:AB43) -> 100374.97 | AC44: =SUM(AC13:AC43) -> 50049.53 | AD44: =SUM(AD13:AD43) -> 43521.33 | AE44: =SUM(AE13:AE43) -> 173556.33 | AF44: =SUM(AF13:AF43) -> 143896.3

Sheet May 2026
B2: NOIR Cinemas - Unaizah
B3: Managed & Operated by - Mukta A2 Cinemas
B5: Cinema | D5: Noir Cinema | G5: Month | I5: 46143
B6: Location | D6: Unizah | G6: Financial Year | I6: 2026
B7: Screens | D7: 4 | G7: VAT | I7: 0.15
B8: Seats | D8: 238 | G8: GCAM | I8: 0.1
G10: Box Office | P10: Concession | AA10: Total Box Office Revenue | AC10: Total Concession Revenue | AE10: Grand Total Revenue
B11: Date | C11: Day | D11: Seats | E11: Total Shows | F11: Total Available Capacity | G11: Admits | H11: Box Office Revenue | I11: ATP | J11: Occ % | K11: VAT (15%) | L11: Net BO Rev Before GCAM | M11: GCAM | N11: Net BO Rev After GCAM | P11: Concession Rev | Q11: SPH | R11: Transaction | S11: ASR | T11: VAT | U11: Net Concession Revenue | V11: Items Sold | W11: Concession Conversion % | X11: Concessions Standard Cost | Y11: COGS | AA11: Gross | AB11: Nett | AC11: Gross | AD11: Nett | AE11: Gross | AF11: Nett
B12: TOTAL MTD | D12: =D44 -> 238 | E12: =E44 -> 551 | F12: =F44 -> 32481 | G12: =G44 -> 4122 | H12: =H44 -> 137751.18 | I12: =I44 -> 33.41853 | J12: =J44 -> 0.12690496 | K12: =K44 -> 17967.545 | ... N12: =N44 -> 110092.17 | P12: =P44 -> 53778.71 | Q12: =Q44 -> 13.046752 | R12: =R44 -> 1375 | S12: =S44 -> 0.33357593 | T12: =T44 -> 7014.6143 | U12: =U44 -> 46764.096 | V12: =V44 -> 2627 | W12: =W44 -> 0.63731198 | ... Y12: =Y44 -> 0.19948452 | AA12: =AA44 -> 137751.18 | AB12: =AB44 -> 110092.17 | AC12: =AC44 -> 53778.71 | AD12: =AD44 -> 46764.096 | AE12: =AE44 -> 191529.89 | AF12: =AF44 -> 156856.27
B13: 46143 | C13: Friday | D13: 238 | E13: 17 | F13: 982 | G13: 442 | H13: 15007.18 | I13: =H13/G13 -> 33.952896 | J13: =G13/F13 -> 0.45010183 | K13: =H13*15/115 -> 1957.4583 | L13: =H13-K13 -> 13049.722 | M13: 1169.26 | N13: =L13-M13 -> 11880.462 | P13: 4052 | Q13: =P13/G13 -> 9.1674208 | R13: 100 | S13: =(R13/G13) -> 0.22624434 | T13: =P13*15/115 -> 528.52174 | U13: =P13-T13 -> 3523.4783 | V13: 201 | W13: =V13/G13 -> 0.45475113 | X13: 746.21 | Y13: =(X13/P13) -> 0.18415844 | AA13: =H13 -> 15007.18 | AB13: =N13 -> 11880.462 | AC13: =P13 -> 4052 | AD13: =U13 -> 3523.4783 | AE13: =AA13+AC13 -> 19059.18 | AF13: =AB13+AD13 -> 15403.94
B14: 46144 | C14: Saturday | D14: 238 | E14: 20 | F14: 1183 | G14: 91 | H14: 3032 | I14: =H14/G14 -> 33.318681 | J14: =G14/F14 -> 0.076923077 | K14: =H14*15/115 -> 395.47826 | L14: =H14-K14 -> 2636.5217 | M14: 219.15 | N14: =L14-M14 -> 2417.3717 | P14: 1244 | Q14: =P14/G14 -> 13.67033 | R14: 34 | S14: =(R14/G14) -> 0.37362637 | T14: =P14*15/115 -> 162.26087 | U14: =P14-T14 -> 1081.7391 | V14: 63 | W14: =V14/G14 -> 0.69230769 | X14: 209.13 | Y14: =(X14/P14) -> 0.16811093 | AA14: =H14 -> 3032 | AB14: =N14 -> 2417.3717 | AC14: =P14 -> 1244 | AD14: =U14 -> 1081.7391 | AE14: =AA14+AC14 -> 4276 | AF14: =AB14+AD14 -> 3499.1109
B15: 46145 | C15: Sunday | D15: 238 | E15: 14 | F15: 808 | G15: 36 | H15: 1165.6 | I15: =H15/G15 -> 32.377778 | J15: =G15/F15 -> 0.044554455 | K15: =H15*15/115 -> 152.03478 | L15: =H15-K15 -> 1013.5652 | M15: 93.02 | N15: =L15-M15 -> 920.54522 | P15: 450 | Q15: =P15/G15 -> 12.5 | R15: 22 | S15: =(R15/G15) -> 0.61111111 | T15: =P15*15/115 -> 58.695652 | U15: =P15-T15 -> 391.30435 | V15: 35 | W15: =V15/G15 -> 0.97222222 | X15: 158.62 | Y15: =(X15/P15) -> 0.35248889 | AA15: =H15 -> 1165.6 | AB15: =N15 -> 920.54522 | AC15: =P15 -> 450 | AD15: =U15 -> 391.30435 | AE15: =AA15+AC15 -> 1615.6 | AF15: =AB15+AD15 -> 1311.8496
B16: 46146 | C16: Monday | D16: 238 | E16: 14 | F16: 808 | G16: 27 | H16: 864 | I16: =H16/G16 -> 32 | J16: =G16/F16 -> 0.033415842 | K16: =H16*15/115 -> 112.69565 | L16: =H16-K16 -> 751.30435 | M16: 36.18 | N16: =L16-M16 -> 715.12435 | P16: 489 | Q16: =P16/G16 -> 18.111111 | R16: 13 | S16: =(R16/G16) -> 0.48148148 | T16: =P16*15/115 -> 63.782609 | U16: =P16-T16 -> 425.21739 | V16: 29 | W16: =V16/G16 -> 1.0740741 | X16: 86.26 | Y16: =(X16/P16) -> 0.17640082 | AA16: =H16 -> 864 | AB16: =N16 -> 715.12435 | AC16: =P16 -> 489 | AD16: =U16 -> 425.21739 | AE16: =AA16+AC16 -> 1353 | AF16: =AB16+AD16 -> 1140.3417
B17: 46147 | C17: Tuesday | D17: 238 | E17: 14 | F17: 808 | G17: 37 | H17: 1002 | I17: =H17/G17 -> 27.081081 | J17: =G17/F17 -> 0.045792079 | K17: =H17*15/115 -> 130.69565 | L17: =H17-K17 -> 871.30435 | M17: 76.01 | N17: =L17-M17 -> 795.29435 | P17: 981 | Q17: =P17/G17 -> 26.513514 | R17: 19 | S17: =(R17/G17) -> 0.51351351 | T17: =P17*15/115 -> 127.95652 | U17: =P17-T17 -> 853.04348 | V17: 45 | W17: =V17/G17 -> 1.2162162 | X17: 180.48 | Y17: =(X17/P17) -> 0.18397554 | AA17: =H17 -> 1002 | AB17: =N17 -> 795.29435 | AC17: =P17 -> 981 | AD17: =U17 -> 853.04348 | AE17: =AA17+AC17 -> 1983 | AF17: =AB17+AD17 -> 1648.3378
B18: 46148 | C18: Wednesday | D18: 238 | E18: 14 | F18: 808 | G18: 50 | H18: 1640 | I18: =H18/G18 -> 32.8 | J18: =G18/F18 -> 0.061881188 | K18: =H18*15/115 -> 213.91304 | L18: =H18-K18 -> 1426.087 | M18: 131.49 | N18: =L18-M18 -> 1294.597 | P18: 977 | Q18: =P18/G18 -> 19.54 | R18: 23 | S18: =(R18/G18) -> 0.46 | T18: =P18*15/115 -> 127.43478 | U18: =P18-T18 -> 849.56522 | V18: 67 | W18: =V18/G18 -> 1.34 | X18: 346.78 | Y18: =(X18/P18) -> 0.35494371 | AA18: =H18 -> 1640 | AB18: =N18 -> 1294.597 | AC18: =P18 -> 977 | AD18: =U18 -> 849.56522 | AE18: =AA18+AC18 -> 2617 | AF18: =AB18+AD18 -> 2144.1622
B19: 46149 | C19: Thursday | D19: 238 | E19: 16 | F19: 952 | G19: 53 | H19: 1706 | I19: =H19/G19 -> 32.188679 | J19: =G19/F19 -> 0.055672269 | K19: =H19*15/115 -> 222.52174 | L19: =H19-K19 -> 1483.4783 | M19: 123.32 | N19: =L19-M19 -> 1360.1583 | P19: 1541 | Q19: =P19/G19 -> 29.075472 | R19: 36 | S19: =(R19/G19) -> 0.67924528 | T19: =P19*15/115 -> 201 | U19: =P19-T19 -> 1340 | V19: 85 | W19: =V19/G19 -> 1.6037736 | X19: 295.04 | Y19: =(X19/P19) -> 0.19146009 | AA19: =H19 -> 1706 | AB19: =N19 -> 1360.1583 | AC19: =P19 -> 1541 | AD19: =U19 -> 1340 | AE19: =AA19+AC19 -> 3247 | AF19: =AB19+AD19 -> 2700.1583
B20: 46150 | C20: Friday | D20: 238 | E20: 17 | F20: 1016 | G20: 130 | H20: 4410 | I20: =H20/G20 -> 33.923077 | J20: =G20/F20 -> 0.12795276 | K20: =H20*15/115 -> 575.21739 | L20: =H20-K20 -> 3834.7826 | M20: 288.2 | N20: =L20-M20 -> 3546.5826 | P20: 2753 | Q20: =P20/G20 -> 21.176923 | R20: 66 | S20: =(R20/G20) -> 0.50769231 | T20: =P20*15/115 -> 359.08696 | U20: =P20-T20 -> 2393.913 | V20: 141 | W20: =V20/G20 -> 1.0846154 | X20: 493 | Y20: =(X20/P20) -> 0.17907737 | AA20: =H20 -> 4410 | AB20: =N20 -> 3546.5826 | AC20: =P20 -> 2753 | AD20: =U20 -> 2393.913 | AE20: =AA20+AC20 -> 7163 | AF20: =AB20+AD20 -> 5940.4957
B21: 46151 | C21: Saturday | D21: 238 | E21: 18 | F21: 1073 | G21: 26 | H21: 942 | I21: =H21/G21 -> 36.230769 | J21: =G21/F21 -> 0.024231128 | K21: =H21*15/115 -> 122.86957 | L21: =H21-K21 -> 819.13043 | M21: 63.48 | N21: =L21-M21 -> 755.65043 | P21: 876 | Q21: =P21/G21 -> 33.692308 | R21: 24 | S21: =(R21/G21) -> 0.92307692 | T21: =P21*15/115 -> 114.26087 | U21: =P21-T21 -> 761.73913 | V21: 38 | W21: =V21/G21 -> 1.4615385 | X21: 148.96 | Y21: =(X21/P21) -> 0.17004566 | AA21: =H21 -> 942 | AB21: =N21 -> 755.65043 | AC21: =P21 -> 876 | AD21: =U21 -> 761.73913 | AE21: =AA21+AC21 -> 1818 | AF21: =AB21+AD21 -> 1517.3896
B22: 46152 | C22: Sunday | D22: 238 | E22: 16 | F22: 952 | G22: 15 | H22: 480 | I22: =H22/G22 -> 32 | J22: =G22/F22 -> 0.015756303 | K22: =H22*15/115 -> 62.608696 | L22: =H22-K22 -> 417.3913 | M22: 41.75 | N22: =L22-M22 -> 375.6413 | P22: 503.6 | Q22: =P22/G22 -> 33.573333 | R22: 14 | S22: =(R22/G22) -> 0.93333333 | T22: =P22*15/115 -> 65.686957 | U22: =P22-T22 -> 437.91304 | V22: 22 | W22: =V22/G22 -> 1.4666667 | X22: 117.76 | Y22: =(X22/P22) -> 0.23383638 | AA22: =H22 -> 480 | AB22: =N22 -> 375.6413 | AC22: =P22 -> 503.6 | AD22: =U22 -> 437.91304 | AE22: =AA22+AC22 -> 983.6 | AF22: =AB22+AD22 -> 813.55435
B23: 46153 | C23: Monday | D23: 238 | E23: 16 | F23: 952 | G23: 25 | H23: 800 | I23: =H23/G23 -> 32 | J23: =G23/F23 -> 0.026260504 | K23: =H23*15/115 -> 104.34783 | L23: =H23-K23 -> 695.65217 | M23: 13.91 | N23: =L23-M23 -> 681.74217 | P23: 523 | Q23: =P23/G23 -> 20.92 | R23: 16 | S23: =(R23/G23) -> 0.64 | T23: =P23*15/115 -> 68.217391 | U23: =P23-T23 -> 454.78261 | V23: 33 | W23: =V23/G23 -> 1.32 | X23: 93.6 | Y23: =(X23/P23) -> 0.1789675 | AA23: =H23 -> 800 | AB23: =N23 -> 681.74217 | AC23: =P23 -> 523 | AD23: =U23 -> 454.78261 | AE23: =AA23+AC23 -> 1323 | AF23: =AB23+AD23 -> 1136.5248
B24: 46154 | C24: Tuesday | D24: 238 | E24: 16 | F24: 952 | G24: 28 | H24: 714 | I24: =H24/G24 -> 25.5 | J24: =G24/F24 -> 0.029411765 | K24: =H24*15/115 -> 93.130435 | L24: =H24-K24 -> 620.86957 | M24: 25.92 | N24: =L24-M24 -> 594.94957 | P24: 749 | Q24: =P24/G24 -> 26.75 | R24: 19 | S24: =(R24/G24) -> 0.67857143 | T24: =P24*15/115 -> 97.695652 | U24: =P24-T24 -> 651.30435 | V24: 44 | W24: =V24/G24 -> 1.5714286 | X24: 135.42 | Y24: =(X24/P24) -> 0.18080107 | AA24: =H24 -> 714 | AB24: =N24 -> 594.94957 | AC24: =P24 -> 749 | AD24: =U24 -> 651.30435 | AE24: =AA24+AC24 -> 1463 | AF24: =AB24+AD24 -> 1246.2539
... B42: 46172 | C42: Saturday | D42: 238 | E42: 24 | F42: 1444 | G42: 142 | H42: 4774 | I42: =H42/G42 -> 33.619718 | J42: =G42/F42 -> 0.09833795 | K42: =H42*15/115 -> 622.69565 | L42: =H42-K42 -> 4151.3043 | M42: 166.1 | N42: =L42-M42 -> 3985.2043 | P42: 3064 | Q42: =P42/G42 -> 21.577465 | R42: 79 | S42: =(R42/G42) -> 0.55633803 | T42: =P42*15/115 -> 399.65217 | U42: =P42-T42 -> 2664.3478 | V42: 117 | W42: =V42/G42 -> 0.82394366 | X42: 693.81 | Y42: =(X42/P42) -> 0.2264393 | AA42: =H42 -> 4774 | AB42: =N42 -> 3985.2043 | AC42: =P42 -> 3064 | AD42: =U42 -> 2664.3478 | AE42: =AA42+AC42 -> 7838 | AF42: =AB42+AD42 -> 6649.5522
B43: 46173 | C43: Sunday | D43: 238 | E43: 24 | F43: 1444 | G43: 184 | H43: 6312.4 | I43: =H43/G43 -> 34.306522 | J43: =G43/F43 -> 0.12742382 | K43: =H43*15/115 -> 823.35652 | L43: =H43-K43 -> 5489.0435 | N43: =L43-M43 -> 5489.0435 | P43: 3554.61 | Q43: =P43/G43 -> 19.318533 | R43: 74 | S43: =(R43/G43) -> 0.40217391 | T43: =P43*15/115 -> 463.64478 | U43: =P43-T43 -> 3090.9652 | V43: 131 | W43: =V43/G43 -> 0.71195652 | X43: 700.42 | Y43: =(X43/P43) -> 0.19704553 | AA43: =H43 -> 6312.4 | AB43: =N43 -> 5489.0435 | AC43: =P43 -> 3554.61 | AD43: =U43 -> 3090.9652 | AE43: =AA43+AC43 -> 9867.01 | AF43: =AB43+AD43 -> 8580.0087
B44: TOTAL | D44: =AVERAGE(D13:D43) -> 238 | E44: =SUM(E13:E43) -> 551 | F44: =SUM(F13:F43) -> 32481 | G44: =SUM(G13:G43) -> 4122 | H44: =SUM(H13:H43) -> 137751.18 | I44: =H44/G44 -> 33.41853 | J44: =(G44/F44) -> 0.12690496 | K44: =SUM(K13:K43) -> 17967.545 | L44: =SUM(L13:L43) -> 119783.63 | M44: =SUM(M13:M43) -> 9691.46 | N44: =SUM(N13:N43) -> 110092.17 | P44: =SUM(P13:P43) -> 53778.71 | Q44: =P44/G44 -> 13.046752 | R44: =SUM(R13:R43) -> 1375 | S44: =(R44/G44) -> 0.33357593 | T44: =SUM(T13:T43) -> 7014.6143 | U44: =SUM(U13:U43) -> 46764.096 | V44: =SUM(V13:V43) -> 2627 | W44: =V44/G44 -> 0.63731198 | X44: =SUM(X13:X43) -> 10728.02 | Y44: =(X44/P44) -> 0.19948452 | AA44: =SUM(AA13:AA43) -> 137751.18 | AB44: =SUM(AB13:AB43) -> 110092.17 | AC44: =SUM(AC13:AC43) -> 53778.71 | AD44: =SUM(AD13:AD43) -> 46764.096 | AE44: =SUM(AE13:AE43) -> 191529.89 | AF44: =SUM(AF13:AF43) -> 156856.27

Sheet Jun 2026
B2: NOIR Cinemas - Unaizah
B3: Managed & Operated by - Mukta A2 Cinemas
B5: Cinema | D5: Noir Cinema | G5: Month | I5: 46174
B6: Location | D6: Unizah | G6: Financial Year | I6: 2026
B7: Screens | D7: 4 | G7: VAT | I7: 0.15
B8: Seats | D8: 238 | G8: GCAM | I8: 0.1
G10: Box Office | P10: Concession | AA10: Total Box Office Revenue | AC10: Total Concession Revenue | AE10: Grand Total Revenue
B11: Date | C11: Day | D11: Seats | E11: Total Shows | F11: Total Available Capacity | G11: Admits | H11: Box Office Revenue | I11: ATP | J11: Occ % | K11: VAT (15%) | L11: Net BO Rev Before GCAM | M11: GCAM | N11: Net BO Rev After GCAM | P11: Concession Rev | Q11: SPH | R11: Transaction | S11: ASR | T11: VAT | U11: Net Concession Revenue | V11: Items Sold | W11: Concession Conversion % | X11: Concessions Standard Cost | Y11: COGS | AA11: Gross | AB11: Nett | AC11: Gross | AD11: Nett | AE11: Gross | AF11: Nett
B12: TOTAL MTD | D12: =D44 -> 238 | E12: =E44 -> 555 | F12: =F44 -> 33301 | G12: =G44 -> 1990 | H12: =H44 -> 52414 | I12: =I44 -> 26.338693 | J12: =J44 -> 0.059757965 | K12: =K44 -> 6836.6087 | ... N12: =N44 -> 42444.231 | P12: =P44 -> 36984.27 | Q12: =Q44 -> 18.58506 | R12: =R44 -> 867 | S12: =S44 -> 0.43567839 | T12: =T44 -> 4824.0352 | U12: =U44 -> 32160.235 | V12: =V44 -> 1802 | W12: =W44 -> 0.90552764 | ... Y12: =Y44 -> 0.19599954 | AA12: =AA44 -> 52414 | AB12: =AB44 -> 42444.231 | AC12: =AC44 -> 36984.27 | AD12: =AD44 -> 32160.235 | AE12: =AE44 -> 89398.27 | AF12: =AF44 -> 74604.466
B13: 46174 | C13: Monday | D13: 238 | E13: 19 | F13: 1126 | G13: 100 | H13: 3200 | I13: =IFERROR(H13/G13,0) -> 32 | J13: =IFERROR(G13/F13,0) -> 0.088809947 | K13: =H13*15/115 -> 417.3913 | L13: =H13-K13 -> 2782.6087 | M13: 44.53 | N13: =L13-M13 -> 2738.0787 | P13: 2348 | Q13: =IFERROR(P13/G13,0) -> 23.48 | R13: 48 | S13: =IFERROR((R13/G13),0) -> 0.48 | T13: =P13*15/115 -> 306.26087 | U13: =P13-T13 -> 2041.7391 | V13: 100 | W13: =IFERROR(V13/G13,0) -> 1 | X13: 468.21 | Y13: =IFERROR((X13/P13),0) -> 0.19940801 | AA13: =H13 -> 3200 | AB13: =N13 -> 2738.0787 | AC13: =P13 -> 2348 | AD13: =U13 -> 2041.7391 | AE13: =AA13+AC13 -> 5548 | AF13: =AB13+AD13 -> 4779.8178
B14: 46175 | C14: Tuesday | D14: 238 | E14: 19 | F14: 1126 | G14: 64 | H14: 2146 | I14: =IFERROR(H14/G14,0) -> 33.53125 | J14: =IFERROR(G14/F14,0) -> 0.056838366 | K14: =H14*15/115 -> 279.91304 | L14: =H14-K14 -> 1866.087 | M14: 16.7 | N14: =L14-M14 -> 1849.387 | P14: 1600 | Q14: =IFERROR(P14/G14,0) -> 25 | R14: 28 | S14: =IFERROR((R14/G14),0) -> 0.4375 | T14: =P14*15/115 -> 208.69565 | U14: =P14-T14 -> 1391.3043 | V14: 80 | W14: =IFERROR(V14/G14,0) -> 1.25 | X14: 303.81 | Y14: =IFERROR((X14/P14),0) -> 0.18988125 | AA14: =H14 -> 2146 | AB14: =N14 -> 1849.387 | AC14: =P14 -> 1600 | AD14: =U14 -> 1391.3043 | AE14: =AA14+AC14 -> 3746 | AF14: =AB14+AD14 -> 3240.6913
B15: 46176 | C15: Wednesday | D15: 238 | E15: 19 | F15: 1126 | G15: 77 | H15: 2624 | I15: =IFERROR(H15/G15,0) -> 34.077922 | J15: =IFERROR(G15/F15,0) -> 0.068383659 | K15: =H15*15/115 -> 342.26087 | L15: =H15-K15 -> 2281.7391 | M15: 24 | N15: =L15-M15 -> 2257.7391 | P15: 1513 | Q15: =IFERROR(P15/G15,0) -> 19.649351 | R15: 32 | S15: =IFERROR((R15/G15),0) -> 0.41558442 | T15: =P15*15/115 -> 197.34783 | U15: =P15-T15 -> 1315.6522 | V15: 80 | W15: =IFERROR(V15/G15,0) -> 1.038961 | X15: 266.37 | Y15: =IFERROR((X15/P15),0) -> 0.1760542 | AA15: =H15 -> 2624 | AB15: =N15 -> 2257.7391 | AC15: =P15 -> 1513 | AD15: =U15 -> 1315.6522 | AE15: =AA15+AC15 -> 4137 | AF15: =AB15+AD15 -> 3573.3913
B16: 46177 | C16: Thursday | D16: 238 | E16: 17 | F16: 1032 | G16: 114 | H16: 3798 | I16: =IFERROR(H16/G16,0) -> 33.315789 | J16: =IFERROR(G16/F16,0) -> 0.11046512 | K16: =H16*15/115 -> 495.3913 | L16: =H16-K16 -> 3302.6087 | M16: 198.8 | N16: =L16-M16 -> 3103.8087 | P16: 1286 | Q16: =IFERROR(P16/G16,0) -> 11.280702 | R16: 34 | S16: =IFERROR((R16/G16),0) -> 0.29824561 | T16: =P16*15/115 -> 167.73913 | U16: =P16-T16 -> 1118.2609 | V16: 70 | W16: =IFERROR(V16/G16,0) -> 0.61403509 | X16: 202.42 | Y16: =IFERROR((X16/P16),0) -> 0.1574028 | AA16: =H16 -> 3798 | AB16: =N16 -> 3103.8087 | AC16: =P16 -> 1286 | AD16: =U16 -> 1118.2609 | AE16: =AA16+AC16 -> 5084 | AF16: =AB16+AD16 -> 4222.0696
B17: 46178 | C17: Friday | D17: 238 | E17: 17 | F17: 1032 | G17: 150 | H17: 4980 | I17: =IFERROR(H17/G17,0) -> 33.2 | J17: =IFERROR(G17/F17,0) -> 0.14534884 | K17: =H17*15/115 -> 649.56522 | L17: =H17-K17 -> 4330.4348 | M17: 290.47 | N17: =L17-M17 -> 4039.9648 | P17: 1580 | Q17: =IFERROR(P17/G17,0) -> 10.533333 | R17: 37 | S17: =IFERROR((R17/G17),0) -> 0.24666667 | T17: =P17*15/115 -> 206.08696 | U17: =P17-T17 -> 1373.913 | V17: 86 | W17: =IFERROR(V17/G17,0) -> 0.57333333 | X17: 292.01 | Y17: =IFERROR((X17/P17),0) -> 0.18481646 | AA17: =H17 -> 4980 | AB17: =N17 -> 4039.9648 | AC17: =P17 -> 1580 | AD17: =U17 -> 1373.913 | AE17: =AA17+AC17 -> 6560 | AF17: =AB17+AD17 -> 5413.8778
B18: 46179 | C18: Saturday | D18: 238 | E18: 21 | F18: 1270 | G18: 58 | H18: 1936 | I18: =IFERROR(H18/G18,0) -> 33.37931 | J18: =IFERROR(G18/F18,0) -> 0.045669291 | K18: =H18*15/115 -> 252.52174 | L18: =H18-K18 -> 1683.4783 | M18: 103.66 | N18: =L18-M18 -> 1579.8183 | P18: 876 | Q18: =IFERROR(P18/G18,0) -> 15.103448 | R18: 28 | S18: =IFERROR((R18/G18),0) -> 0.48275862 | T18: =P18*15/115 -> 114.26087 | U18: =P18-T18 -> 761.73913 | V18: 50 | W18: =IFERROR(V18/G18,0) -> 0.86206897 | X18: 168.09 | Y18: =IFERROR((X18/P18),0) -> 0.19188356 | AA18: =H18 -> 1936 | AB18: =N18 -> 1579.8183 | AC18: =P18 -> 876 | AD18: =U18 -> 761.73913 | AE18: =AA18+AC18 -> 2812 | AF18: =AB18+AD18 -> 2341.5574
B19: 46180 | C19: Sunday | D19: 238 | E19: 17 | F19: 1032 | G19: 28 | H19: 936 | I19: =IFERROR(H19/G19,0) -> 33.428571 | J19: =IFERROR(G19/F19,0) -> 0.027131783 | K19: =H19*15/115 -> 122.08696 | L19: =H19-K19 -> 813.91304 | M19: 19.48 | N19: =L19-M19 -> 794.43304 | P19: 345 | Q19: =IFERROR(P19/G19,0) -> 12.321429 | R19: 13 | S19: =IFERROR((R19/G19),0) -> 0.46428571 | T19: =P19*15/115 -> 45 | U19: =P19-T19 -> 300 | V19: 20 | W19: =IFERROR(V19/G19,0) -> 0.71428571 | X19: 59.25 | Y19: =IFERROR((X19/P19),0) -> 0.17173913 | AA19: =H19 -> 936 | AB19: =N19 -> 794.43304 | AC19: =P19 -> 345 | AD19: =U19 -> 300 | AE19: =AA19+AC19 -> 1281 | AF19: =AB19+AD19 -> 1094.433
B20: 46181 | C20: Monday | D20: 238 | E20: 17 | F20: 1032 | G20: 25 | H20: 800 | I20: =IFERROR(H20/G20,0) -> 32 | J20: =IFERROR(G20/F20,0) -> 0.024224806 | K20: =H20*15/115 -> 104.34783 | L20: =H20-K20 -> 695.65217 | M20: 8.35 | N20: =L20-M20 -> 687.30217 | P20: 454.8 | Q20: =IFERROR(P20/G20,0) -> 18.192 | R20: 17 | S20: =IFERROR((R20/G20),0) -> 0.68 | T20: =P20*15/115 -> 59.321739 | U20: =P20-T20 -> 395.47826 | V20: 22 | W20: =IFERROR(V20/G20,0) -> 0.88 | X20: 81.14 | Y20: =IFERROR((X20/P20),0) -> 0.17840809 | AA20: =H20 -> 800 | AB20: =N20 -> 687.30217 | AC20: =P20 -> 454.8 | AD20: =U20 -> 395.47826 | AE20: =AA20+AC20 -> 1254.8 | AF20: =AB20+AD20 -> 1082.7804
B21: 46182 | C21: Tuesday | D21: 238 | E21: 17 | F21: 1032 | G21: 22 | H21: 628 | I21: =IFERROR(H21/G21,0) -> 28.545455 | J21: =IFERROR(G21/F21,0) -> 0.021317829 | K21: =H21*15/115 -> 81.913043 | L21: =H21-K21 -> 546.08696 | M21: 37.92 | N21: =L21-M21 -> 508.16696 | P21: 351 | Q21: =IFERROR(P21/G21,0) -> 15.954545 | R21: 12 | S21: =IFERROR((R21/G21),0) -> 0.54545455 | T21: =P21*15/115 -> 45.782609 | U21: =P21-T21 -> 305.21739 | V21: 19 | W21: =IFERROR(V21/G21,0) -> 0.86363636 | X21: 49.43 | Y21: =IFERROR((X21/P21),0) -> 0.14082621 | AA21: =H21 -> 628 | AB21: =N21 -> 508.16696 | AC21: =P21 -> 351 | AD21: =U21 -> 305.21739 | AE21: =AA21+AC21 -> 979 | AF21: =AB21+AD21 -> 813.38435
B22: 46183 | C22: Wednesday | D22: 238 | E22: 16 | F22: 975 | G22: 38 | H22: 902 | I22: =IFERROR(H22/G22,0) -> 23.736842 | J22: =IFERROR(G22/F22,0) -> 0.038974359 | K22: =H22*15/115 -> 117.65217 | L22: =H22-K22 -> 784.34783 | M22: 40.52 | N22: =L22-M22 -> 743.82783 | P22: 781 | Q22: =IFERROR(P22/G22,0) -> 20.552632 | R22: 21 | S22: =IFERROR((R22/G22),0) -> 0.55263158 | T22: =P22*15/115 -> 101.86957 | U22: =P22-T22 -> 679.13043 | V22: 39 | W22: =IFERROR(V22/G22,0) -> 1.0263158 | X22: 144.47 | Y22: =IFERROR((X22/P22),0) -> 0.18498079 | AA22: =H22 -> 902 | AB22: =N22 -> 743.82783 | AC22: =P22 -> 781 | AD22: =U22 -> 679.13043 | AE22: =AA22+AC22 -> 1683 | AF22: =AB22+AD22 -> 1422.9583
B23: 46184 | C23: Thursday | D23: 238 | E23: 18 | F23: 1069 | G23: 65 | H23: 1648 | I23: =IFERROR(H23/G23,0) -> 25.353846 | J23: =IFERROR(G23/F23,0) -> 0.06080449 | K23: =H23*15/115 -> 214.95652 | L23: =H23-K23 -> 1433.0435 | M23: 109.39 | N23: =L23-M23 -> 1323.6535 | P23: 1469 | Q23: =IFERROR(P23/G23,0) -> 22.6 | R23: 35 | S23: =IFERROR((R23/G23),0) -> 0.53846154 | T23: =P23*15/115 -> 191.6087 | U23: =P23-T23 -> 1277.3913 | V23: 76 | W23: =IFERROR(V23/G23,0) -> 1.1692308 | X23: 269.42 | Y23: =IFERROR((X23/P23),0) -> 0.18340368 | AA23: =H23 -> 1648 | AB23: =N23 -> 1323.6535 | AC23: =P23 -> 1469 | AD23: =U23 -> 1277.3913 | AE23: =AA23+AC23 -> 3117 | AF23: =AB23+AD23 -> 2601.0448
B24: 46185 | C24: Friday | D24: 238 | E24: 18 | F24: 1069 | G24: 94 | H24: 2208 | I24: =IFERROR(H24/G24,0) -> 23.489362 | J24: =IFERROR(G24/F24,0) -> 0.087932647 | K24: =H24*15/115 -> 288 | L24: =H24-K24 -> 1920 | M24: 150.6 | N24: =L24-M24 -> 1769.4 | P24: 1627 | Q24: =IFERROR(P24/G24,0) -> 17.308511 | R24: 32 | S24: =IFERROR((R24/G24),0) -> 0.34042553 | T24: =P24*15/115 -> 212.21739 | U24: =P24-T24 -> 1414.7826 | V24: 77 | W24: =IFERROR(V24/G24,0) -> 0.81914894 | X24: 274.54 | Y24: =IFERROR((X24/P24),0) -> 0.16874001 | AA24: =H24 -> 2208 | AB24: =N24 -> 1769.4 | AC24: =P24 -> 1627 | AD24: =U24 -> 1414.7826 | AE24: =AA24+AC24 -> 3835 | AF24: =AB24+AD24 -> 3184.1826
... B42: 46203 | C42: Tuesday | D42: 238 | E42: 17 | F42: 1036 | G42: 93 | H42: 1900 | I42: =IFERROR(H42/G42,0) -> 20.430108 | J42: =IFERROR(G42/F42,0) -> 0.08976834 | K42: =H42*15/115 -> 247.82609 | L42: =H42-K42 -> 1652.1739 | M42: 199.15 | N42: =L42-M42 -> 1453.0239 | P42: 1748 | Q42: =IFERROR(P42/G42,0) -> 18.795699 | R42: 45 | S42: =IFERROR((R42/G42),0) -> 0.48387097 | T42: =P42*15/115 -> 228 | U42: =P42-T42 -> 1520 | V42: 72 | W42: =IFERROR(V42/G42,0) -> 0.77419355 | X42: 350.59 | Y42: =IFERROR((X42/P42),0) -> 0.20056636 | AA42: =H42 -> 1900 | AB42: =N42 -> 1453.0239 | AC42: =P42 -> 1748 | AD42: =U42 -> 1520 | AE42: =AA42+AC42 -> 3648 | AF42: =AB42+AD42 -> 2973.0239
I43: =IFERROR(H43/G43,0) -> 0 | J43: =IFERROR(G43/F43,0) -> 0 | K43: =H43*15/115 -> 0 | L43: =H43-K43 -> 0 | N43: =L43-M43 -> 0 | Q43: =IFERROR(P43/G43,0) -> 0 | S43: =IFERROR((R43/G43),0) -> 0 | T43: =P43*15/115 -> 0 | U43: =P43-T43 -> 0 | W43: =IFERROR(V43/G43,0) -> 0 | Y43: =IFERROR((X43/P43),0) -> 0 | AA43: =H43 -> 0 | AB43: =N43 -> 0 | AC43: =P43 -> 0 | AD43: =U43 -> 0 | AE43: =AA43+AC43 -> 0 | AF43: =AB43+AD43 -> 0
B44: TOTAL | D44: =AVERAGE(D13:D43) -> 238 | E44: =SUM(E13:E43) -> 555 | F44: =SUM(F13:F43) -> 33301 | G44: =SUM(G13:G43) -> 1990 | H44: =SUM(H13:H43) -> 52414 | I44: =IFERROR(H44/G44,0) -> 26.338693 | J44: =IFERROR((G44/F44),0) -> 0.059757965 | K44: =SUM(K13:K43) -> 6836.6087 | L44: =SUM(L13:L43) -> 45577.391 | M44: =SUM(M13:M43) -> 3133.16 | N44: =SUM(N13:N43) -> 42444.231 | P44: =SUM(P13:P43) -> 36984.27 | Q44: =IFERROR(P44/G44,0) -> 18.58506 | R44: =SUM(R13:R43) -> 867 | S44: =IFERROR((R44/G44),0) -> 0.43567839 | T44: =SUM(T13:T43) -> 4824.0352 | U44: =SUM(U13:U43) -> 32160.235 | V44: =SUM(V13:V43) -> 1802 | W44: =IFERROR(V44/G44,0) -> 0.90552764 | X44: =SUM(X13:X43) -> 7248.9 | Y44: =IFERROR((X44/P44),0) -> 0.19599954 | AA44: =SUM(AA13:AA43) -> 52414 | AB44: =SUM(AB13:AB43) -> 42444.231 | AC44: =SUM(AC13:AC43) -> 36984.27 | AD44: =SUM(AD13:AD43) -> 32160.235 | AE44: =SUM(AE13:AE43) -> 89398.27 | AF44: =SUM(AF13:AF43) -> 74604.466

Sheet Jul 2026
B2: NOIR Cinemas - Unaizah
B3: Managed & Operated by - Mukta A2 Cinemas
B5: Cinema | D5: Noir Cinema | G5: Month | I5: 46204
B6: Location | D6: Unizah | G6: Financial Year | I6: 2026
B7: Screens | D7: 4 | G7: VAT | I7: 0.15
B8: Seats | D8: 238 | G8: GCAM | I8: 0.1
G10: Box Office | P10: Concession | AA10: Total Box Office Revenue | AC10: Total Concession Revenue | AE10: Grand Total Revenue
B11: Date | C11: Day | D11: Seats | E11: Total Shows | F11: Total Available Capacity | G11: Admits | H11: Box Office Revenue | I11: ATP | J11: Occ % | K11: VAT (15%) | L11: Net BO Rev Before GCAM | M11: GCAM | N11: Net BO Rev After GCAM | P11: Concession Rev | Q11: SPH | R11: Transaction | S11: ASR | T11: VAT | U11: Net Concession Revenue | V11: Items Sold | W11: Concession Conversion % | X11: Concessions Standard Cost | Y11: COGS | AA11: Gross | AB11: Nett | AC11: Gross | AD11: Nett | AE11: Gross | AF11: Nett
B12: TOTAL MTD | D12: =D44 -> 238 | E12: =E44 -> 603 | F12: =F44 -> 35215 | G12: =G44 -> 2303 | H12: =H44 -> 51129.5 | I12: =I44 -> 22.201259 | J12: =J44 -> 0.065398268 | K12: =K44 -> 6669.0652 | ... N12: =N44 -> 40435.105 | P12: =P44 -> 46102.47 | Q12: =Q44 -> 20.018441 | R12: =R44 -> 1031 | S12: =S44 -> 0.44767694 | T12: =T44 -> 6013.3657 | U12: =U44 -> 40089.104 | V12: =V44 -> 2156 | W12: =W44 -> 0.93617021 | ... Y12: =Y44 -> 0.19380176 | AA12: =AA44 -> 51129.5 | AB12: =AB44 -> 40435.105 | AC12: =AC44 -> 46102.47 | AD12: =AD44 -> 40089.104 | AE12: =AE44 -> 97231.97 | AF12: =AF44 -> 80524.209
B13: 46204 | C13: Wednesday | D13: 238 | E13: 17 | F13: 1036 | G13: 92 | H13: 1948 | I13: =IFERROR(H13/G13,0) -> 21.173913 | J13: =IFERROR(G13/F13,0) -> 0.088803089 | K13: =H13*15/115 -> 254.08696 | L13: =H13-K13 -> 1693.913 | M13: 116.53 | N13: =L13-M13 -> 1577.383 | P13: 2292 | Q13: =IFERROR(P13/G13,0) -> 24.913043 | R13: 47 | S13: =IFERROR((R13/G13),0) -> 0.51086957 | T13: =P13*15/115 -> 298.95652 | U13: =P13-T13 -> 1993.0435 | V13: 88 | W13: =IFERROR(V13/G13,0) -> 0.95652174 | X13: 431.64 | Y13: =IFERROR((X13/P13),0) -> 0.18832461 | AA13: =H13 -> 1948 | AB13: =N13 -> 1577.383 | AC13: =P13 -> 2292 | AD13: =U13 -> 1993.0435 | AE13: =AA13+AC13 -> 4240 | AF13: =AB13+AD13 -> 3570.4265
B14: 46205 | C14: Thursday | D14: 238 | E14: 25 | F14: 1508 | G14: 86 | H14: 1838 | I14: =IFERROR(H14/G14,0) -> 21.372093 | J14: =IFERROR(G14/F14,0) -> 0.057029178 | K14: =H14*15/115 -> 239.73913 | L14: =H14-K14 -> 1598.2609 | M14: 110.08 | N14: =L14-M14 -> 1488.1809 | P14: 1523.11 | Q14: =IFERROR(P14/G14,0) -> 17.710581 | R14: 35 | S14: =IFERROR((R14/G14),0) -> 0.40697674 | T14: =P14*15/115 -> 198.66652 | U14: =P14-T14 -> 1324.4435 | V14: 88 | W14: =IFERROR(V14/G14,0) -> 1.0232558 | X14: 297.53 | Y14: =IFERROR((X14/P14),0) -> 0.19534374 | AA14: =H14 -> 1838 | AB14: =N14 -> 1488.1809 | AC14: =P14 -> 1523.11 | AD14: =U14 -> 1324.4435 | AE14: =AA14+AC14 -> 3361.11 | AF14: =AB14+AD14 -> 2812.6243
B15: 46206 | C15: Friday | D15: 238 | E15: 18 | F15: 1069 | G15: 103 | H15: 2368 | I15: =IFERROR(H15/G15,0) -> 22.990291 | J15: =IFERROR(G15/F15,0) -> 0.096351731 | K15: =H15*15/115 -> 308.86957 | L15: =H15-K15 -> 2059.1304 | M15: 175.29 | N15: =L15-M15 -> 1883.8404 | P15: 1871.29 | Q15: =IFERROR(P15/G15,0) -> 18.167864 | R15: 50 | S15: =IFERROR((R15/G15),0) -> 0.48543689 | T15: =P15*15/115 -> 244.0813 | U15: =P15-T15 -> 1627.2087 | V15: 84 | W15: =IFERROR(V15/G15,0) -> 0.81553398 | X15: 359.63 | Y15: =IFERROR((X15/P15),0) -> 0.19218293 | AA15: =H15 -> 2368 | AB15: =N15 -> 1883.8404 | AC15: =P15 -> 1871.29 | AD15: =U15 -> 1627.2087 | AE15: =AA15+AC15 -> 4239.29 | AF15: =AB15+AD15 -> 3511.0491
B16: 46207 | C16: Saturday | D16: 238 | E16: 21 | F16: 1227 | G16: 61 | H16: 1378 | I16: =IFERROR(H16/G16,0) -> 22.590164 | J16: =IFERROR(G16/F16,0) -> 0.049714751 | K16: =H16*15/115 -> 179.73913 | L16: =H16-K16 -> 1198.2609 | M16: 101.56 | N16: =L16-M16 -> 1096.7009 | P16: 1525 | Q16: =IFERROR(P16/G16,0) -> 25 | R16: 34 | S16: =IFERROR((R16/G16),0) -> 0.55737705 | T16: =P16*15/115 -> 198.91304 | U16: =P16-T16 -> 1326.087 | V16: 79 | W16: =IFERROR(V16/G16,0) -> 1.295082 | X16: 265.9 | Y16: =IFERROR((X16/P16),0) -> 0.17436066 | AA16: =H16 -> 1378 | AB16: =N16 -> 1096.7009 | AC16: =P16 -> 1525 | AD16: =U16 -> 1326.087 | AE16: =AA16+AC16 -> 2903 | AF16: =AB16+AD16 -> 2422.7878
B17: 46208 | C17: Sunday | D17: 238 | E17: 18 | F17: 1069 | G17: 58 | H17: 1296 | I17: =IFERROR(H17/G17,0) -> 22.344828 | J17: =IFERROR(G17/F17,0) -> 0.054256314 | K17: =H17*15/115 -> 169.04348 | L17: =H17-K17 -> 1126.9565 | M17: 86.44 | N17: =L17-M17 -> 1040.5165 | P17: 1979 | Q17: =IFERROR(P17/G17,0) -> 34.12069 | R17: 37 | S17: =IFERROR((R17/G17),0) -> 0.63793103 | T17: =P17*15/115 -> 258.13043 | U17: =P17-T17 -> 1720.8696 | V17: 88 | W17: =IFERROR(V17/G17,0) -> 1.5172414 | X17: 346 | Y17: =IFERROR((X17/P17),0) -> 0.17483578 | AA17: =H17 -> 1296 | AB17: =N17 -> 1040.5165 | AC17: =P17 -> 1979 | AD17: =U17 -> 1720.8696 | AE17: =AA17+AC17 -> 3275 | AF17: =AB17+AD17 -> 2761.3861
B18: 46209 | C18: Monday | D18: 238 | E18: 18 | F18: 1069 | G18: 58 | H18: 1152 | I18: =IFERROR(H18/G18,0) -> 19.862069 | J18: =IFERROR(G18/F18,0) -> 0.054256314 | K18: =H18*15/115 -> 150.26087 | L18: =H18-K18 -> 1001.7391 | M18: 65.4 | N18: =L18-M18 -> 936.33913 | P18: 1004.72 | Q18: =IFERROR(P18/G18,0) -> 17.322759 | R18: 26 | S18: =IFERROR((R18/G18),0) -> 0.44827586 | T18: =P18*15/115 -> 131.05043 | U18: =P18-T18 -> 873.66957 | V18: 55 | W18: =IFERROR(V18/G18,0) -> 0.94827586 | X18: 216.42 | Y18: =IFERROR((X18/P18),0) -> 0.2154033 | AA18: =H18 -> 1152 | AB18: =N18 -> 936.33913 | AC18: =P18 -> 1004.72 | AD18: =U18 -> 873.66957 | AE18: =AA18+AC18 -> 2156.72 | AF18: =AB18+AD18 -> 1810.0087
B19: 46210 | C19: Tuesday | D19: 238 | E19: 17 | F19: 989 | G19: 65 | H19: 1504 | I19: =IFERROR(H19/G19,0) -> 23.138462 | J19: =IFERROR(G19/F19,0) -> 0.065722952 | K19: =H19*15/115 -> 196.17391 | L19: =H19-K19 -> 1307.8261 | M19: 100.71 | N19: =L19-M19 -> 1207.1161 | P19: 1204 | Q19: =IFERROR(P19/G19,0) -> 18.523077 | R19: 26 | S19: =IFERROR((R19/G19),0) -> 0.4 | T19: =P19*15/115 -> 157.04348 | U19: =P19-T19 -> 1046.9565 | V19: 56 | W19: =IFERROR(V19/G19,0) -> 0.86153846 | X19: 236.58 | Y19: =IFERROR((X19/P19),0) -> 0.19649502 | AA19: =H19 -> 1504 | AB19: =N19 -> 1207.1161 | AC19: =P19 -> 1204 | AD19: =U19 -> 1046.9565 | AE19: =AA19+AC19 -> 2708 | AF19: =AB19+AD19 -> 2254.0726
B20: 46211 | C20: Wednesday | D20: 238 | E20: 18 | F20: 1069 | G20: 78 | H20: 1536 | I20: =IFERROR(H20/G20,0) -> 19.692308 | J20: =IFERROR(G20/F20,0) -> 0.072965388 | K20: =H20*15/115 -> 200.34783 | L20: =H20-K20 -> 1335.6522 | M20: 88.7 | N20: =L20-M20 -> 1246.9522 | P20: 1672 | Q20: =IFERROR(P20/G20,0) -> 21.435897 | R20: 37 | S20: =IFERROR((R20/G20),0) -> 0.47435897 | T20: =P20*15/115 -> 218.08696 | U20: =P20-T20 -> 1453.913 | V20: 81 | W20: =IFERROR(V20/G20,0) -> 1.0384615 | X20: 283.07 | Y20: =IFERROR((X20/P20),0) -> 0.16930024 | AA20: =H20 -> 1536 | AB20: =N20 -> 1246.9522 | AC20: =P20 -> 1672 | AD20: =U20 -> 1453.913 | AE20: =AA20+AC20 -> 3208 | AF20: =AB20+AD20 -> 2700.8652
B21: 46212 | C21: Thursday | D21: 238 | E21: 25 | F21: 1422 | G21: 90 | H21: 1587 | I21: =IFERROR(H21/G21,0) -> 17.633333 | J21: =IFERROR(G21/F21,0) -> 0.063291139 | K21: =H21*15/115 -> 207 | L21: =H21-K21 -> 1380 | M21: 116.43 | N21: =L21-M21 -> 1263.57 | P21: 1832 | Q21: =IFERROR(P21/G21,0) -> 20.355556 | R21: 43 | S21: =IFERROR((R21/G21),0) -> 0.47777778 | T21: =P21*15/115 -> 238.95652 | U21: =P21-T21 -> 1593.0435 | V21: 69 | W21: =IFERROR(V21/G21,0) -> 0.76666667 | X21: 362.95 | Y21: =IFERROR((X21/P21),0) -> 0.19811681 | AA21: =H21 -> 1587 | AB21: =N21 -> 1263.57 | AC21: =P21 -> 1832 | AD21: =U21 -> 1593.0435 | AE21: =AA21+AC21 -> 3419 | AF21: =AB21+AD21 -> 2856.6135
B22: 46213 | C22: Friday | D22: 238 | E22: 23 | F22: 1328 | G22: 94 | H22: 1892 | I22: =IFERROR(H22/G22,0) -> 20.12766 | J22: =IFERROR(G22/F22,0) -> 0.070783133 | K22: =H22*15/115 -> 246.78261 | L22: =H22-K22 -> 1645.2174 | M22: 149.55 | N22: =L22-M22 -> 1495.6674 | P22: 1611 | Q22: =IFERROR(P22/G22,0) -> 17.138298 | R22: 32 | S22: =IFERROR((R22/G22),0) -> 0.34042553 | T22: =P22*15/115 -> 210.13043 | U22: =P22-T22 -> 1400.8696 | V22: 71 | W22: =IFERROR(V22/G22,0) -> 0.75531915 | X22: 283.47 | Y22: =IFERROR((X22/P22),0) -> 0.17595903 | AA22: =H22 -> 1892 | AB22: =N22 -> 1495.6674 | AC22: =P22 -> 1611 | AD22: =U22 -> 1400.8696 | AE22: =AA22+AC22 -> 3503 | AF22: =AB22+AD22 -> 2896.537
B23: 46214 | C23: Saturday | D23: 238 | E23: 25 | F23: 1449 | G23: 51 | H23: 1213 | I23: =IFERROR(H23/G23,0) -> 23.784314 | J23: =IFERROR(G23/F23,0) -> 0.035196687 | K23: =H23*15/115 -> 158.21739 | L23: =H23-K23 -> 1054.7826 | M23: 88.08 | N23: =L23-M23 -> 966.70261 | P23: 1632 | Q23: =IFERROR(P23/G23,0) -> 32 | R23: 29 | S23: =IFERROR((R23/G23),0) -> 0.56862745 | T23: =P23*15/115 -> 212.86957 | U23: =P23-T23 -> 1419.1304 | V23: 92 | W23: =IFERROR(V23/G23,0) -> 1.8039216 | X23: 283.49 | Y23: =IFERROR((X23/P23),0) -> 0.17370711 | AA23: =H23 -> 1213 | AB23: =N23 -> 966.70261 | AC23: =P23 -> 1632 | AD23: =U23 -> 1419.1304 | AE23: =AA23+AC23 -> 2845 | AF23: =AB23+AD23 -> 2385.833
B24: 46215 | C24: Sunday | D24: 238 | E24: 19 | F24: 1090 | G24: 58 | H24: 1148 | I24: =IFERROR(H24/G24,0) -> 19.793103 | J24: =IFERROR(G24/F24,0) -> 0.053211009 | K24: =H24*15/115 -> 149.73913 | L24: =H24-K24 -> 998.26087 | M24: 78.27 | N24: =L24-M24 -> 919.99087 | P24: 985 | Q24: =IFERROR(P24/G24,0) -> 16.982759 | R24: 20 | S24: =IFERROR((R24/G24),0) -> 0.34482759 | T24: =P24*15/115 -> 128.47826 | U24: =P24-T24 -> 856.52174 | V24: 53 | W24: =IFERROR(V24/G24,0) -> 0.9137931 | X24: 181.06 | Y24: =IFERROR((X24/P24),0) -> 0.18381726 | AA24: =H24 -> 1148 | AB24: =N24 -> 919.99087 | AC24: =P24 -> 985 | AD24: =U24 -> 856.52174 | AE24: =AA24+AC24 -> 2133 | AF24: =AB24+AD24 -> 1776.5126
... B43: 46234 | C43: Friday | D43: 238 | E43: 18 | F43: 1089 | G43: 97 | H43: 3886 | I43: =IFERROR(H43/G43,0) -> 40.061856 | J43: =IFERROR(G43/F43,0) -> 0.089072544 | K43: =H43*15/115 -> 506.86957 | L43: =H43-K43 -> 3379.1304 | M43: 337.89 | N43: =L43-M43 -> 3041.2404 | P43: 1599 | Q43: =IFERROR(P43/G43,0) -> 16.484536 | R43: 38 | S43: =IFERROR((R43/G43),0) -> 0.39175258 | T43: =P43*15/115 -> 208.56522 | U43: =P43-T43 -> 1390.4348 | V43: 66 | W43: =IFERROR(V43/G43,0) -> 0.68041237 | X43: 331.16 | Y43: =IFERROR((X43/P43),0) -> 0.20710444 | AA43: =H43 -> 3886 | AB43: =N43 -> 3041.2404 | AC43: =P43 -> 1599 | AD43: =U43 -> 1390.4348 | AE43: =AA43+AC43 -> 5485 | AF43: =AB43+AD43 -> 4431.6752
B44: TOTAL | D44: =AVERAGE(D13:D43) -> 238 | E44: =SUM(E13:E43) -> 603 | F44: =SUM(F13:F43) -> 35215 | G44: =SUM(G13:G43) -> 2303 | H44: =SUM(H13:H43) -> 51129.5 | I44: =IFERROR(H44/G44,0) -> 22.201259 | J44: =IFERROR((G44/F44),0) -> 0.065398268 | K44: =SUM(K13:K43) -> 6669.0652 | L44: =SUM(L13:L43) -> 44460.435 | M44: =SUM(M13:M43) -> 4025.33 | N44: =SUM(N13:N43) -> 40435.105 | P44: =SUM(P13:P43) -> 46102.47 | Q44: =IFERROR(P44/G44,0) -> 20.018441 | R44: =SUM(R13:R43) -> 1031 | S44: =IFERROR((R44/G44),0) -> 0.44767694 | T44: =SUM(T13:T43) -> 6013.3657 | U44: =SUM(U13:U43) -> 40089.104 | V44: =SUM(V13:V43) -> 2156 | W44: =IFERROR(V44/G44,0) -> 0.93617021 | X44: =SUM(X13:X43) -> 8934.74 | Y44: =IFERROR((X44/P44),0) -> 0.19380176 | AA44: =SUM(AA13:AA43) -> 51129.5 | AB44: =SUM(AB13:AB43) -> 40435.105 | AC44: =SUM(AC13:AC43) -> 46102.47 | AD44: =SUM(AD13:AD43) -> 40089.104 | AE44: =SUM(AE13:AE43) -> 97231.97 | AF44: =SUM(AF13:AF43) -> 80524.209

Sheet Aug 2026
B2: NOIR Cinemas - Unaizah
B3: Managed & Operated by - Mukta A2 Cinemas
B5: Cinema | D5: Noir Cinema | G5: Month | I5: 46235
B6: Location | D6: Unizah | G6: Financial Year | I6: 2026
B7: Screens | D7: 4 | G7: VAT | I7: 0.15
B8: Seats | D8: 238 | G8: GCAM | I8: 0.1
G10: Box Office | P10: Concession | AA10: Total Box Office Revenue | AC10: Total Concession Revenue | AE10: Grand Total Revenue
B11: Date | C11: Day | D11: Seats | E11: Total Shows | F11: Total Available Capacity | G11: Admits | H11: Box Office Revenue | I11: ATP | J11: Occ % | K11: VAT (15%) | L11: Net BO Rev Before GCAM | M11: GCAM | N11: Net BO Rev After GCAM | P11: Concession Rev | Q11: SPH | R11: Transaction | S11: ASR | T11: VAT | U11: Net Concession Revenue | V11: Items Sold | W11: Concession Conversion % | X11: Concessions Standard Cost | Y11: COGS | AA11: Gross | AB11: Nett | AC11: Gross | AD11: Nett | AE11: Gross | AF11: Nett
B12: TOTAL MTD | D12: =D44 -> 238 | E12: =E44 -> 563 | F12: =F44 -> 33311 | G12: =G44 -> 4624 | H12: =H44 -> 142046.72 | I12: =I44 -> 30.719446 | J12: =J44 -> 0.138813 | K12: =K44 -> 18527.833 | ... N12: =N44 -> 112298.04 | P12: =P44 -> 60976.94 | Q12: =Q44 -> 13.187054 | R12: =R44 -> 1526 | S12: =S44 -> 0.3300173 | T12: =T44 -> 7953.5139 | U12: =U44 -> 53023.426 | V12: =V44 -> 2648 | W12: =W44 -> 0.57266436 | ... Y12: =Y44 -> 0.18643868 | AA12: =AA44 -> 142046.72 | AB12: =AB44 -> 112298.04 | AC12: =AC44 -> 60976.94 | AD12: =AD44 -> 53023.426 | AE12: =AE44 -> 203023.66 | AF12: =AF44 -> 165321.46
B13: 46235 | C13: Saturday | D13: 238 | E13: 21 | F13: 1247 | G13: 76 | H13: 2912.39 | I13: =IFERROR(H13/G13,0) -> 38.320921 | J13: =IFERROR(G13/F13,0) -> 0.060946271 | K13: =H13*15/115 -> 379.87696 | L13: =H13-K13 -> 2532.513 | M13: 253.23 | N13: =L13-M13 -> 2279.283 | P13: 1514.39 | Q13: =IFERROR(P13/G13,0) -> 19.926184 | R13: 36 | S13: =IFERROR((R13/G13),0) -> 0.47368421 | T13: =P13*15/115 -> 197.52913 | U13: =P13-T13 -> 1316.8609 | V13: 56 | W13: =IFERROR(V13/G13,0) -> 0.73684211 | X13: 301.92 | Y13: =IFERROR((X13/P13),0) -> 0.1993674 | AA13: =H13 -> 2912.39 | AB13: =N13 -> 2279.283 | AC13: =P13 -> 1514.39 | AD13: =U13 -> 1316.8609 | AE13: =AA13+AC13 -> 4426.78 | AF13: =AB13+AD13 -> 3596.1439
B14: 46236 | C14: Sunday | D14: 238 | E14: 14 | F14: 808 | G14: 153 | H14: 3423.21 | I14: =IFERROR(H14/G14,0) -> 22.373922 | J14: =IFERROR(G14/F14,0) -> 0.18935644 | K14: =H14*15/115 -> 446.50565 | L14: =H14-K14 -> 2976.7043 | M14: 297.7 | N14: =L14-M14 -> 2679.0043 | P14: 3004.2 | Q14: =IFERROR(P14/G14,0) -> 19.635294 | R14: 74 | S14: =IFERROR((R14/G14),0) -> 0.48366013 | T14: =P14*15/115 -> 391.85217 | U14: =P14-T14 -> 2612.3478 | V14: 124 | W14: =IFERROR(V14/G14,0) -> 0.81045752 | X14: 582.07 | Y14: =IFERROR((X14/P14),0) -> 0.19375208 | AA14: =H14 -> 3423.21 | AB14: =N14 -> 2679.0043 | AC14: =P14 -> 3004.2 | AD14: =U14 -> 2612.3478 | AE14: =AA14+AC14 -> 6427.41 | AF14: =AB14+AD14 -> 5291.3522
B15: 46237 | C15: Monday | D15: 238 | E15: 14 | F15: 808 | G15: 164 | H15: 3386 | I15: =IFERROR(H15/G15,0) -> 20.646341 | J15: =IFERROR(G15/F15,0) -> 0.2029703 | K15: =H15*15/115 -> 441.65217 | L15: =H15-K15 -> 2944.3478 | M15: 294.47 | N15: =L15-M15 -> 2649.8778 | P15: 3258 | Q15: =IFERROR(P15/G15,0) -> 19.865854 | R15: 70 | S15: =IFERROR((R15/G15),0) -> 0.42682927 | T15: =P15*15/115 -> 424.95652 | U15: =P15-T15 -> 2833.0435 | V15: 120 | W15: =IFERROR(V15/G15,0) -> 0.73170732 | X15: 626.54 | Y15: =IFERROR((X15/P15),0) -> 0.19230816 | AA15: =H15 -> 3386 | AB15: =N15 -> 2649.8778 | AC15: =P15 -> 3258 | AD15: =U15 -> 2833.0435 | AE15: =AA15+AC15 -> 6644 | AF15: =AB15+AD15 -> 5482.9213
B16: 46238 | C16: Tuesday | D16: 238 | E16: 14 | F16: 808 | G16: 118 | H16: 2344 | I16: =IFERROR(H16/G16,0) -> 19.864407 | J16: =IFERROR(G16/F16,0) -> 0.1460396 | K16: =H16*15/115 -> 305.73913 | L16: =H16-K16 -> 2038.2609 | M16: 203.85 | N16: =L16-M16 -> 1834.4109 | P16: 1810 | Q16: =IFERROR(P16/G16,0) -> 15.338983 | R16: 46 | S16: =IFERROR((R16/G16),0) -> 0.38983051 | T16: =P16*15/115 -> 236.08696 | U16: =P16-T16 -> 1573.913 | V16: 75 | W16: =IFERROR(V16/G16,0) -> 0.63559322 | X16: 360.19 | Y16: =IFERROR((X16/P16),0) -> 0.199 | AA16: =H16 -> 2344 | AB16: =N16 -> 1834.4109 | AC16: =P16 -> 1810 | AD16: =U16 -> 1573.913 | AE16: =AA16+AC16 -> 4154 | AF16: =AB16+AD16 -> 3408.3239
B17: 46239 | C17: Wednesday | D17: 238 | E17: 14 | F17: 808 | G17: 164 | H17: 3490 | I17: =IFERROR(H17/G17,0) -> 21.280488 | J17: =IFERROR(G17/F17,0) -> 0.2029703 | K17: =H17*15/115 -> 455.21739 | L17: =H17-K17 -> 3034.7826 | M17: 303.51 | N17: =L17-M17 -> 2731.2726 | P17: 3493 | Q17: =IFERROR(P17/G17,0) -> 21.29878 | R17: 67 | S17: =IFERROR((R17/G17),0) -> 0.40853659 | T17: =P17*15/115 -> 455.6087 | U17: =P17-T17 -> 3037.3913 | V17: 156 | W17: =IFERROR(V17/G17,0) -> 0.95121951 | X17: 656.67 | Y17: =IFERROR((X17/P17),0) -> 0.18799599 | AA17: =H17 -> 3490 | AB17: =N17 -> 2731.2726 | AC17: =P17 -> 3493 | AD17: =U17 -> 3037.3913 | AE17: =AA17+AC17 -> 6983 | AF17: =AB17+AD17 -> 5768.6639
B18: 46240 | C18: Thursday | D18: 238 | E18: 22 | F18: 1311 | G18: 137 | H18: 5440.78 | I18: =IFERROR(H18/G18,0) -> 39.713723 | J18: =IFERROR(G18/F18,0) -> 0.10450038 | K18: =H18*15/115 -> 709.66696 | L18: =H18-K18 -> 4731.113 | M18: 473.08 | N18: =L18-M18 -> 4258.033 | P18: 2975 | Q18: =IFERROR(P18/G18,0) -> 21.715328 | R18: 72 | S18: =IFERROR((R18/G18),0) -> 0.52554745 | T18: =P18*15/115 -> 388.04348 | U18: =P18-T18 -> 2586.9565 | V18: 117 | W18: =IFERROR(V18/G18,0) -> 0.8540146 | X18: 563.19 | Y18: =IFERROR((X18/P18),0) -> 0.18930756 | AA18: =H18 -> 5440.78 | AB18: =N18 -> 4258.033 | AC18: =P18 -> 2975 | AD18: =U18 -> 2586.9565 | AE18: =AA18+AC18 -> 8415.78 | AF18: =AB18+AD18 -> 6844.9896
B19: 46241 | C19: Friday | D19: 238 | E19: 20 | F19: 1190 | G19: 225 | H19: 8659.56 | I19: =IFERROR(H19/G19,0) -> 38.486933 | J19: =IFERROR(G19/F19,0) -> 0.18907563 | K19: =H19*15/115 -> 1129.5078 | L19: =H19-K19 -> 7530.0522 | M19: 752.94 | N19: =L19-M19 -> 6777.1122 | P19: 2469 | Q19: =IFERROR(P19/G19,0) -> 10.973333 | R19: 62 | S19: =IFERROR((R19/G19),0) -> 0.27555556 | T19: =P19*15/115 -> 322.04348 | U19: =P19-T19 -> 2146.9565 | V19: 95 | W19: =IFERROR(V19/G19,0) -> 0.42222222 | X19: 473.83 | Y19: =IFERROR((X19/P19),0) -> 0.19191171 | AA19: =H19 -> 8659.56 | AB19: =N19 -> 6777.1122 | AC19: =P19 -> 2469 | AD19: =U19 -> 2146.9565 | AE19: =AA19+AC19 -> 11128.56 | AF19: =AB19+AD19 -> 8924.0687
B20: 46242 | C20: Saturday | D20: 238 | E20: 21 | F20: 1247 | G20: 193 | H20: 7608 | I20: =IFERROR(H20/G20,0) -> 39.419689 | J20: =IFERROR(G20/F20,0) -> 0.15477145 | K20: =H20*15/115 -> 992.34783 | L20: =H20-K20 -> 6615.6522 | M20: 661.51 | N20: =L20-M20 -> 5954.1422 | P20: 2323 | Q20: =IFERROR(P20/G20,0) -> 12.036269 | R20: 67 | S20: =IFERROR((R20/G20),0) -> 0.34715026 | T20: =P20*15/115 -> 303 | U20: =P20-T20 -> 2020 | V20: 94 | W20: =IFERROR(V20/G20,0) -> 0.48704663 | X20: 433.98 | Y20: =IFERROR((X20/P20),0) -> 0.18681877 | AA20: =H20 -> 7608 | AB20: =N20 -> 5954.1422 | AC20: =P20 -> 2323 | AD20: =U20 -> 2020 | AE20: =AA20+AC20 -> 9931 | AF20: =AB20+AD20 -> 7974.1422
B21: 46243 | C21: Sunday | D21: 238 | E21: 16 | F21: 952 | G21: 182 | H21: 4298 | I21: =IFERROR(H21/G21,0) -> 23.615385 | J21: =IFERROR(G21/F21,0) -> 0.19117647 | K21: =H21*15/115 -> 560.6087 | L21: =H21-K21 -> 3737.3913 | M21: 373.78 | N21: =L21-M21 -> 3363.6113 | P21: 2400 | Q21: =IFERROR(P21/G21,0) -> 13.186813 | R21: 65 | S21: =IFERROR((R21/G21),0) -> 0.35714286 | T21: =P21*15/115 -> 313.04348 | U21: =P21-T21 -> 2086.9565 | V21: 110 | W21: =IFERROR(V21/G21,0) -> 0.6043956 | X21: 441.55 | Y21: =IFERROR((X21/P21),0) -> 0.18397917 | AA21: =H21 -> 4298 | AB21: =N21 -> 3363.6113 | AC21: =P21 -> 2400 | AD21: =U21 -> 2086.9565 | AE21: =AA21+AC21 -> 6698 | AF21: =AB21+AD21 -> 5450.5678
B22: 46244 | C22: Monday | D22: 238 | E22: 16 | F22: 952 | G22: 135 | H22: 2734 | I22: =IFERROR(H22/G22,0) -> 20.251852 | J22: =IFERROR(G22/F22,0) -> 0.14180672 | K22: =H22*15/115 -> 356.6087 | L22: =H22-K22 -> 2377.3913 | M22: 237.77 | N22: =L22-M22 -> 2139.6213 | P22: 1614 | Q22: =IFERROR(P22/G22,0) -> 11.955556 | R22: 44 | S22: =IFERROR((R22/G22),0) -> 0.32592593 | T22: =P22*15/115 -> 210.52174 | U22: =P22-T22 -> 1403.4783 | V22: 68 | W22: =IFERROR(V22/G22,0) -> 0.5037037 | X22: 297.94 | Y22: =IFERROR((X22/P22),0) -> 0.18459727 | AA22: =H22 -> 2734 | AB22: =N22 -> 2139.6213 | AC22: =P22 -> 1614 | AD22: =U22 -> 1403.4783 | AE22: =AA22+AC22 -> 4348 | AF22: =AB22+AD22 -> 3543.0996
B23: 46245 | C23: Tuesday | D23: 238 | E23: 16 | F23: 952 | G23: 125 | H23: 2672 | I23: =IFERROR(H23/G23,0) -> 21.376 | J23: =IFERROR(G23/F23,0) -> 0.13130252 | K23: =H23*15/115 -> 348.52174 | L23: =H23-K23 -> 2323.4783 | M23: 232.37 | N23: =L23-M23 -> 2091.1083 | P23: 2767 | Q23: =IFERROR(P23/G23,0) -> 22.136 | R23: 64 | S23: =IFERROR((R23/G23),0) -> 0.512 | T23: =P23*15/115 -> 360.91304 | U23: =P23-T23 -> 2406.087 | V23: 123 | W23: =IFERROR(V23/G23,0) -> 0.984 | X23: 488.49 | Y23: =IFERROR((X23/P23),0) -> 0.17654138 | AA23: =H23 -> 2672 | AB23: =N23 -> 2091.1083 | AC23: =P23 -> 2767 | AD23: =U23 -> 2406.087 | AE23: =AA23+AC23 -> 5439 | AF23: =AB23+AD23 -> 4497.1952
B24: 46246 | C24: Wednesday | D24: 238 | E24: 16 | F24: 952 | G24: 119 | H24: 2282 | I24: =IFERROR(H24/G24,0) -> 19.176471 | J24: =IFERROR(G24/F24,0) -> 0.125 | K24: =H24*15/115 -> 297.65217 | L24: =H24-K24 -> 1984.3478 | M24: 160.37 | N24: =L24-M24 -> 1823.9778 | P24: 1831 | Q24: =IFERROR(P24/G24,0) -> 15.386555 | R24: 52 | S24: =IFERROR((R24/G24),0) -> 0.43697479 | T24: =P24*15/115 -> 238.82609 | U24: =P24-T24 -> 1592.1739 | V24: 74 | W24: =IFERROR(V24/G24,0) -> 0.62184874 | X24: 348 | Y24: =IFERROR((X24/P24),0) -> 0.19006008 | AA24: =H24 -> 2282 | AB24: =N24 -> 1823.9778 | AC24: =P24 -> 1831 | AD24: =U24 -> 1592.1739 | AE24: =AA24+AC24 -> 4113 | AF24: =AB24+AD24 -> 3416.1517
... B43: 46265 | C43: Monday | D43: 238 | E43: 16 | F43: 952 | G43: 105 | H43: 2384 | I43: =IFERROR(H43/G43,0) -> 22.704762 | J43: =IFERROR(G43/F43,0) -> 0.11029412 | K43: =H43*15/115 -> 310.95652 | L43: =H43-K43 -> 2073.0435 | M43: 184.02 | N43: =L43-M43 -> 1889.0235 | P43: 1130 | Q43: =IFERROR(P43/G43,0) -> 10.761905 | R43: 23 | S43: =IFERROR((R43/G43),0) -> 0.21904762 | T43: =P43*15/115 -> 147.3913 | U43: =P43-T43 -> 982.6087 | V43: 50 | W43: =IFERROR(V43/G43,0) -> 0.47619048 | X43: 207.38 | Y43: =IFERROR((X43/P43),0) -> 0.18352212 | AA43: =H43 -> 2384 | AB43: =N43 -> 1889.0235 | AC43: =P43 -> 1130 | AD43: =U43 -> 982.6087 | AE43: =AA43+AC43 -> 3514 | AF43: =AB43+AD43 -> 2871.6322
B44: TOTAL | D44: =AVERAGE(D13:D43) -> 238 | E44: =SUM(E13:E43) -> 563 | F44: =SUM(F13:F43) -> 33311 | G44: =SUM(G13:G43) -> 4624 | H44: =SUM(H13:H43) -> 142046.72 | I44: =IFERROR(H44/G44,0) -> 30.719446 | J44: =IFERROR((G44/F44),0) -> 0.138813 | K44: =SUM(K13:K43) -> 18527.833 | L44: =SUM(L13:L43) -> 123518.89 | M44: =SUM(M13:M43) -> 11220.85 | N44: =SUM(N13:N43) -> 112298.04 | P44: =SUM(P13:P43) -> 60976.94 | Q44: =IFERROR(P44/G44,0) -> 13.187054 | R44: =SUM(R13:R43) -> 1526 | S44: =IFERROR((R44/G44),0) -> 0.3300173 | T44: =SUM(T13:T43) -> 7953.5139 | U44: =SUM(U13:U43) -> 53023.426 | V44: =SUM(V13:V43) -> 2648 | W44: =IFERROR(V44/G44,0) -> 0.57266436 | X44: =SUM(X13:X43) -> 11368.46 | Y44: =IFERROR((X44/P44),0) -> 0.18643868 | AA44: =SUM(AA13:AA43) -> 142046.72 | AB44: =SUM(AB13:AB43) -> 112298.04 | AC44: =SUM(AC13:AC43) -> 60976.94 | AD44: =SUM(AD13:AD43) -> 53023.426 | AE44: =SUM(AE13:AE43) -> 203023.66 | AF44: =SUM(AF13:AF43) -> 165321.46

Sheet Sep 2026
B2: NOIR Cinemas - Unaizah
B3: Managed & Operated by - Mukta A2 Cinemas
B5: Cinema | D5: Noir Cinema | G5: Month | I5: 46266
B6: Location | D6: Unizah | G6: Financial Year | I6: 2026
B7: Screens | D7: 4 | G7: VAT | I7: 0.15
B8: Seats | D8: 238 | G8: GCAM | I8: 0.1
G10: Box Office | P10: Concession | AA10: Total Box Office Revenue | AC10: Total Concession Revenue | AE10: Grand Total Revenue
B11: Date | C11: Day | D11: Seats | E11: Total Shows | F11: Total Available Capacity | G11: Admits | H11: Box Office Revenue | I11: ATP | J11: Occ % | K11: VAT (15%) | L11: Net BO Rev Before GCAM | M11: GCAM | N11: Net BO Rev After GCAM | P11: Concession Rev | Q11: SPH | R11: Transaction | S11: ASR | T11: VAT | U11: Net Concession Revenue | V11: Items Sold | W11: Concession Conversion % | X11: Concessions Standard Cost | Y11: COGS | AA11: Gross | AB11: Nett | AC11: Gross | AD11: Nett | AE11: Gross | AF11: Nett
B12: TOTAL MTD | D12: =D43 -> 238 | E12: =E43 -> 537 | F12: =F43 -> 32243 | G12: =G43 -> 1491 | H12: =H43 -> 48128 | I12: =I43 -> 32.279007 | J12: =J43 -> 0.046242595 | K12: =K43 -> 6277.5652 | ... N12: =N43 -> 38249.635 | P12: =P43 -> 22398 | Q12: =Q43 -> 15.022133 | R12: =R43 -> 575 | S12: =S43 -> 0.38564722 | T12: =T43 -> 2921.4783 | U12: =U43 -> 19476.522 | V12: =V43 -> 957 | W12: =W43 -> 0.64185111 | ... Y12: =Y43 -> 0.16997678 | AA12: =AA43 -> 48128 | AB12: =AB43 -> 38249.635 | AC12: =AC43 -> 22398 | AD12: =AD43 -> 19476.522 | AE12: =AE43 -> 70526 | AF12: =AF43 -> 57726.157
B13: 46266 | C13: Tuesday | D13: 238 | E13: 16 | F13: 952 | G13: 98 | H13: 2198 | I13: =IFERROR(H13/G13,0) -> 22.428571 | J13: =IFERROR(G13/F13,0) -> 0.10294118 | K13: =H13*15/115 -> 286.69565 | L13: =H13-K13 -> 1911.3043 | M13: 181.41 | N13: =L13-M13 -> 1729.8943 | P13: 947 | Q13: =IFERROR(P13/G13,0) -> 9.6632653 | R13: 23 | S13: =IFERROR((R13/G13),0) -> 0.23469388 | T13: =P13*15/115 -> 123.52174 | U13: =P13-T13 -> 823.47826 | V13: 38 | W13: =IFERROR(V13/G13,0) -> 0.3877551 | X13: 147.11 | Y13: =IFERROR((X13/P13),0) -> 0.15534319 | AA13: =H13 -> 2198 | AB13: =N13 -> 1729.8943 | AC13: =P13 -> 947 | AD13: =U13 -> 823.47826 | AE13: =AA13+AC13 -> 3145 | AF13: =AB13+AD13 -> 2553.3726
B14: 46267 | C14: Wednesday | D14: 238 | E14: 16 | F14: 952 | G14: 121 | H14: 2846 | I14: =IFERROR(H14/G14,0) -> 23.520661 | J14: =IFERROR(G14/F14,0) -> 0.12710084 | K14: =H14*15/115 -> 371.21739 | L14: =H14-K14 -> 2474.7826 | M14: 203.15 | N14: =L14-M14 -> 2271.6326 | P14: 1346 | Q14: =IFERROR(P14/G14,0) -> 11.123967 | R14: 28 | S14: =IFERROR((R14/G14),0) -> 0.23140496 | T14: =P14*15/115 -> 175.56522 | U14: =P14-T14 -> 1170.4348 | V14: 51 | W14: =IFERROR(V14/G14,0) -> 0.4214876 | X14: 201.09 | Y14: =IFERROR((X14/P14),0) -> 0.14939822 | AA14: =H14 -> 2846 | AB14: =N14 -> 2271.6326 | AC14: =P14 -> 1346 | AD14: =U14 -> 1170.4348 | AE14: =AA14+AC14 -> 4192 | AF14: =AB14+AD14 -> 3442.0674
B15: 46268 | C15: Thursday | D15: 238 | E15: 18 | F15: 1096 | G15: 176 | H15: 7098 | I15: =IFERROR(H15/G15,0) -> 40.329545 | J15: =IFERROR(G15/F15,0) -> 0.16058394 | K15: =H15*15/115 -> 925.82609 | L15: =H15-K15 -> 6172.1739 | M15: 553.18 | N15: =L15-M15 -> 5618.9939 | P15: 1389 | Q15: =IFERROR(P15/G15,0) -> 7.8920455 | R15: 36 | S15: =IFERROR((R15/G15),0) -> 0.20454545 | T15: =P15*15/115 -> 181.17391 | U15: =P15-T15 -> 1207.8261 | V15: 63 | W15: =IFERROR(V15/G15,0) -> 0.35795455 | X15: 202.93 | Y15: =IFERROR((X15/P15),0) -> 0.14609791 | AA15: =H15 -> 7098 | AB15: =N15 -> 5618.9939 | AC15: =P15 -> 1389 | AD15: =U15 -> 1207.8261 | AE15: =AA15+AC15 -> 8487 | AF15: =AB15+AD15 -> 6826.82
B16: 46269 | C16: Friday | D16: 238 | E16: 17 | F16: 1032 | G16: 140 | H16: 5650 | I16: =IFERROR(H16/G16,0) -> 40.357143 | J16: =IFERROR(G16/F16,0) -> 0.13565891 | K16: =H16*15/115 -> 736.95652 | L16: =H16-K16 -> 4913.0435 | M16: 366.75 | N16: =L16-M16 -> 4546.2935 | P16: 2309 | Q16: =IFERROR(P16/G16,0) -> 16.492857 | R16: 53 | S16: =IFERROR((R16/G16),0) -> 0.37857143 | T16: =P16*15/115 -> 301.17391 | U16: =P16-T16 -> 2007.8261 | V16: 99 | W16: =IFERROR(V16/G16,0) -> 0.70714286 | X16: 368.81 | Y16: =IFERROR((X16/P16),0) -> 0.15972715 | AA16: =H16 -> 5650 | AB16: =N16 -> 4546.2935 | AC16: =P16 -> 2309 | AD16: =U16 -> 2007.8261 | AE16: =AA16+AC16 -> 7959 | AF16: =AB16+AD16 -> 6554.1196
B17: 46270 | C17: Saturday | D17: 238 | E17: 21 | F17: 1270 | G17: 60 | H17: 2350 | I17: =IFERROR(H17/G17,0) -> 39.166667 | J17: =IFERROR(G17/F17,0) -> 0.047244094 | K17: =H17*15/115 -> 306.52174 | L17: =H17-K17 -> 2043.4783 | M17: 191.11 | N17: =L17-M17 -> 1852.3683 | P17: 906 | Q17: =IFERROR(P17/G17,0) -> 15.1 | R17: 20 | S17: =IFERROR((R17/G17),0) -> 0.33333333 | T17: =P17*15/115 -> 118.17391 | U17: =P17-T17 -> 787.82609 | V17: 41 | W17: =IFERROR(V17/G17,0) -> 0.68333333 | X17: 139.15 | Y17: =IFERROR((X17/P17),0) -> 0.1535872 | AA17: =H17 -> 2350 | AB17: =N17 -> 1852.3683 | AC17: =P17 -> 906 | AD17: =U17 -> 787.82609 | AE17: =AA17+AC17 -> 3256 | AF17: =AB17+AD17 -> 2640.1943
B18: 46271 | C18: Sunday | D18: 238 | E18: 16 | F18: 952 | G18: 62 | H18: 1368 | I18: =IFERROR(H18/G18,0) -> 22.064516 | J18: =IFERROR(G18/F18,0) -> 0.06512605 | K18: =H18*15/115 -> 178.43478 | L18: =H18-K18 -> 1189.5652 | M18: 97.4 | N18: =L18-M18 -> 1092.1652 | P18: 555 | Q18: =IFERROR(P18/G18,0) -> 8.9516129 | R18: 13 | S18: =IFERROR((R18/G18),0) -> 0.20967742 | T18: =P18*15/115 -> 72.391304 | U18: =P18-T18 -> 482.6087 | V18: 24 | W18: =IFERROR(V18/G18,0) -> 0.38709677 | X18: 98.4 | Y18: =IFERROR((X18/P18),0) -> 0.1772973 | AA18: =H18 -> 1368 | AB18: =N18 -> 1092.1652 | AC18: =P18 -> 555 | AD18: =U18 -> 482.6087 | AE18: =AA18+AC18 -> 1923 | AF18: =AB18+AD18 -> 1574.7739
B19: 46272 | C19: Monday | D19: 238 | E19: 16 | F19: 952 | G19: 40 | H19: 788 | I19: =IFERROR(H19/G19,0) -> 19.7 | J19: =IFERROR(G19/F19,0) -> 0.042016807 | K19: =H19*15/115 -> 102.78261 | L19: =H19-K19 -> 685.21739 | M19: 52.01 | N19: =L19-M19 -> 633.20739 | P19: 533 | Q19: =IFERROR(P19/G19,0) -> 13.325 | R19: 11 | S19: =IFERROR((R19/G19),0) -> 0.275 | T19: =P19*15/115 -> 69.521739 | U19: =P19-T19 -> 463.47826 | V19: 17 | W19: =IFERROR(V19/G19,0) -> 0.425 | X19: 97.91 | Y19: =IFERROR((X19/P19),0) -> 0.18369606 | AA19: =H19 -> 788 | AB19: =N19 -> 633.20739 | AC19: =P19 -> 533 | AD19: =U19 -> 463.47826 | AE19: =AA19+AC19 -> 1321 | AF19: =AB19+AD19 -> 1096.6857
B20: 46273 | C20: Tuesday | D20: 238 | E20: 16 | F20: 952 | G20: 23 | H20: 520 | I20: =IFERROR(H20/G20,0) -> 22.608696 | J20: =IFERROR(G20/F20,0) -> 0.024159664 | K20: =H20*15/115 -> 67.826087 | L20: =H20-K20 -> 452.17391 | M20: 42.27 | N20: =L20-M20 -> 409.90391 | P20: 400 | Q20: =IFERROR(P20/G20,0) -> 17.391304 | R20: 10 | S20: =IFERROR((R20/G20),0) -> 0.43478261 | T20: =P20*15/115 -> 52.173913 | U20: =P20-T20 -> 347.82609 | V20: 18 | W20: =IFERROR(V20/G20,0) -> 0.7826087 | X20: 75.75 | Y20: =IFERROR((X20/P20),0) -> 0.189375 | AA20: =H20 -> 520 | AB20: =N20 -> 409.90391 | AC20: =P20 -> 400 | AD20: =U20 -> 347.82609 | AE20: =AA20+AC20 -> 920 | AF20: =AB20+AD20 -> 757.73
B21: 46274 | C21: Wednesday | D21: 238 | E21: 16 | F21: 952 | G21: 37 | H21: 954 | I21: =IFERROR(H21/G21,0) -> 25.783784 | J21: =IFERROR(G21/F21,0) -> 0.038865546 | K21: =H21*15/115 -> 124.43478 | L21: =H21-K21 -> 829.56522 | M21: 49.05 | N21: =L21-M21 -> 780.51522 | P21: 562 | Q21: =IFERROR(P21/G21,0) -> 15.189189 | R21: 10 | S21: =IFERROR((R21/G21),0) -> 0.27027027 | T21: =P21*15/115 -> 73.304348 | U21: =P21-T21 -> 488.69565 | V21: 20 | W21: =IFERROR(V21/G21,0) -> 0.54054054 | X21: 95.65 | Y21: =IFERROR((X21/P21),0) -> 0.17019573 | AA21: =H21 -> 954 | AB21: =N21 -> 780.51522 | AC21: =P21 -> 562 | AD21: =U21 -> 488.69565 | AE21: =AA21+AC21 -> 1516 | AF21: =AB21+AD21 -> 1269.2109
B22: 46275 | C22: Thursday | D22: 238 | E22: 18 | F22: 1112 | G22: 106 | H22: 4756 | I22: =IFERROR(H22/G22,0) -> 44.867925 | J22: =IFERROR(G22/F22,0) -> 0.095323741 | K22: =H22*15/115 -> 620.34783 | L22: =H22-K22 -> 4135.6522 | M22: 360.7 | N22: =L22-M22 -> 3774.9522 | P22: 794 | Q22: =IFERROR(P22/G22,0) -> 7.490566 | R22: 21 | S22: =IFERROR((R22/G22),0) -> 0.19811321 | T22: =P22*15/115 -> 103.56522 | U22: =P22-T22 -> 690.43478 | V22: 37 | W22: =IFERROR(V22/G22,0) -> 0.3490566 | X22: 130.81 | Y22: =IFERROR((X22/P22),0) -> 0.16474811 | AA22: =H22 -> 4756 | AB22: =N22 -> 3774.9522 | AC22: =P22 -> 794 | AD22: =U22 -> 690.43478 | AE22: =AA22+AC22 -> 5550 | AF22: =AB22+AD22 -> 4465.387
B23: 46276 | C23: Friday | D23: 238 | E23: 17 | F23: 1032 | G23: 92 | H23: 3556 | I23: =IFERROR(H23/G23,0) -> 38.652174 | J23: =IFERROR(G23/F23,0) -> 0.089147287 | K23: =H23*15/115 -> 463.82609 | L23: =H23-K23 -> 3092.1739 | M23: 276.15 | N23: =L23-M23 -> 2816.0239 | P23: 1017 | Q23: =IFERROR(P23/G23,0) -> 11.054348 | R23: 27 | S23: =IFERROR((R23/G23),0) -> 0.29347826 | T23: =P23*15/115 -> 132.65217 | U23: =P23-T23 -> 884.34783 | V23: 48 | W23: =IFERROR(V23/G23,0) -> 0.52173913 | X23: 155.16 | Y23: =IFERROR((X23/P23),0) -> 0.15256637 | AA23: =H23 -> 3556 | AB23: =N23 -> 2816.0239 | AC23: =P23 -> 1017 | AD23: =U23 -> 884.34783 | AE23: =AA23+AC23 -> 4573 | AF23: =AB23+AD23 -> 3700.3717
B24: 46277 | C24: Saturday | D24: 238 | E24: 20 | F24: 1233 | G24: 9 | H24: 342 | I24: =IFERROR(H24/G24,0) -> 38 | J24: =IFERROR(G24/F24,0) -> 0.0072992701 | K24: =H24*15/115 -> 44.608696 | L24: =H24-K24 -> 297.3913 | M24: 29.74 | N24: =L24-M24 -> 267.6513 | P24: 171 | Q24: =IFERROR(P24/G24,0) -> 19 | R24: 6 | S24: =IFERROR((R24/G24),0) -> 0.66666667 | T24: =P24*15/115 -> 22.304348 | U24: =P24-T24 -> 148.69565 | V24: 7 | W24: =IFERROR(V24/G24,0) -> 0.77777778 | X24: 22.04 | Y24: =IFERROR((X24/P24),0) -> 0.12888889 | AA24: =H24 -> 342 | AB24: =N24 -> 267.6513 | AC24: =P24 -> 171 | AD24: =U24 -> 148.69565 | AE24: =AA24+AC24 -> 513 | AF24: =AB24+AD24 -> 416.34696
... B42: 46295 | C42: Wednesday | D42: 238 | E42: 16 | F42: 952 | G42: 9 | H42: 218 | I42: =IFERROR(H42/G42,0) -> 24.222222 | J42: =IFERROR(G42/F42,0) -> 0.0094537815 | K42: =H42*15/115 -> 28.434783 | L42: =H42-K42 -> 189.56522 | M42: 18.96 | N42: =L42-M42 -> 170.60522 | P42: 96 | Q42: =IFERROR(P42/G42,0) -> 10.666667 | R42: 4 | S42: =IFERROR((R42/G42),0) -> 0.44444444 | T42: =P42*15/115 -> 12.521739 | U42: =P42-T42 -> 83.478261 | V42: 5 | W42: =IFERROR(V42/G42,0) -> 0.55555556 | X42: 10.9 | Y42: =IFERROR((X42/P42),0) -> 0.11354167 | AA42: =H42 -> 218 | AB42: =N42 -> 170.60522 | AC42: =P42 -> 96 | AD42: =U42 -> 83.478261 | AE42: =AA42+AC42 -> 314 | AF42: =AB42+AD42 -> 254.08348
B43: TOTAL | D43: =AVERAGE(D13:D42) -> 238 | E43: =SUM(E13:E42) -> 537 | F43: =SUM(F13:F42) -> 32243 | G43: =SUM(G13:G42) -> 1491 | H43: =SUM(H13:H42) -> 48128 | I43: =IFERROR(H43/G43,0) -> 32.279007 | J43: =IFERROR((G43/F43),0) -> 0.046242595 | K43: =SUM(K13:K42) -> 6277.5652 | L43: =SUM(L13:L42) -> 41850.435 | M43: =SUM(M13:M42) -> 3600.8 | N43: =SUM(N13:N42) -> 38249.635 | P43: =SUM(P13:P42) -> 22398 | Q43: =IFERROR(P43/G43,0) -> 15.022133 | R43: =SUM(R13:R42) -> 575 | S43: =IFERROR((R43/G43),0) -> 0.38564722 | T43: =SUM(T13:T42) -> 2921.4783 | U43: =SUM(U13:U42) -> 19476.522 | V43: =SUM(V13:V42) -> 957 | W43: =IFERROR(V43/G43,0) -> 0.64185111 | X43: =SUM(X13:X42) -> 3807.14 | Y43: =IFERROR((X43/P43),0) -> 0.16997678 | AA43: =SUM(AA13:AA42) -> 48128 | AB43: =SUM(AB13:AB42) -> 38249.635 | AC43: =SUM(AC13:AC42) -> 22398 | AD43: =SUM(AD13:AD42) -> 19476.522 | AE43: =SUM(AE13:AE42) -> 70526 | AF43: =SUM(AF13:AF42) -> 57726.157

Sheet Oct 2026
B2: NOIR Cinemas - Unaizah
B3: Managed & Operated by - Mukta A2 Cinemas
B5: Cinema | D5: Noir Cinema | G5: Month | I5: 46296
B6: Location | D6: Unizah | G6: Financial Year | I6: 2026
B7: Screens | D7: 4 | G7: VAT | I7: 0.15
B8: Seats | D8: 238 | G8: GCAM | I8: 0.1
G10: Box Office | P10: Concession | AA10: Total Box Office Revenue | AC10: Total Concession Revenue | AE10: Grand Total Revenue
B11: Date | C11: Day | D11: Seats | E11: Total Shows | F11: Total Available Capacity | G11: Admits | H11: Box Office Revenue | I11: ATP | J11: Occ % | K11: VAT (15%) | L11: Net BO Rev Before GCAM | M11: GCAM | N11: Net BO Rev After GCAM | P11: Concession Rev | Q11: SPH | R11: Transaction | S11: ASR | T11: VAT | U11: Net Concession Revenue | V11: Items Sold | W11: Concession Conversion % | X11: Concessions Standard Cost | Y11: COGS | AA11: Gross | AB11: Nett | AC11: Gross | AD11: Nett | AE11: Gross | AF11: Nett
B12: TOTAL MTD | D12: =D44 -> 238 | E12: =E44 -> 34 | F12: =F44 -> 1978 | G12: =G44 -> 94 | H12: =H44 -> 3722 | I12: =I44 -> 39.595745 | J12: =J44 -> 0.04752275 | K12: =K44 -> 485.47826 | ... N12: =N44 -> 2964.2017 | P12: =P44 -> 2520 | Q12: =Q44 -> 26.808511 | R12: =R44 -> 60 | S12: =S44 -> 0.63829787 | T12: =T44 -> 328.69565 | U12: =U44 -> 2191.3043 | V12: =V44 -> 120 | W12: =W44 -> 1.2765957 | ... Y12: =Y44 -> 0.16684921 | AA12: =AA44 -> 3722 | AB12: =AB44 -> 2964.2017 | AC12: =AC44 -> 2520 | AD12: =AD44 -> 2191.3043 | AE12: =AE44 -> 6242 | AF12: =AF44 -> 5155.5061
B13: 46296 | C13: Thursday | D13: 238 | E13: 17 | F13: 989 | G13: 55 | H13: 2180 | I13: =IFERROR(H13/G13,0) -> 39.636364 | J13: =IFERROR(G13/F13,0) -> 0.055611729 | K13: =H13*15/115 -> 284.34783 | L13: =H13-K13 -> 1895.6522 | M13: 176.33 | N13: =L13-M13 -> 1719.3222 | P13: 1277 | Q13: =IFERROR(P13/G13,0) -> 23.218182 | R13: 28 | S13: =IFERROR((R13/G13),0) -> 0.50909091 | T13: =P13*15/115 -> 166.56522 | U13: =P13-T13 -> 1110.4348 | V13: 60 | W13: =IFERROR(V13/G13,0) -> 1.0909091 | X13: 213.18 | Y13: =IFERROR((X13/P13),0) -> 0.16693814 | AA13: =H13 -> 2180 | AB13: =N13 -> 1719.3222 | AC13: =P13 -> 1277 | AD13: =U13 -> 1110.4348 | AE13: =AA13+AC13 -> 3457 | AF13: =AB13+AD13 -> 2829.757
B14: 46297 | C14: Friday | D14: 238 | E14: 17 | F14: 989 | G14: 39 | H14: 1542 | I14: =IFERROR(H14/G14,0) -> 39.538462 | J14: =IFERROR(G14/F14,0) -> 0.039433771 | K14: =H14*15/115 -> 201.13043 | L14: =H14-K14 -> 1340.8696 | M14: 95.99 | N14: =L14-M14 -> 1244.8796 | P14: 1243 | Q14: =IFERROR(P14/G14,0) -> 31.871795 | R14: 32 | S14: =IFERROR((R14/G14),0) -> 0.82051282 | T14: =P14*15/115 -> 162.13043 | U14: =P14-T14 -> 1080.8696 | V14: 60 | W14: =IFERROR(V14/G14,0) -> 1.5384615 | X14: 207.28 | Y14: =IFERROR((X14/P14),0) -> 0.16675784 | AA14: =H14 -> 1542 | AB14: =N14 -> 1244.8796 | AC14: =P14 -> 1243 | AD14: =U14 -> 1080.8696 | AE14: =AA14+AC14 -> 2785 | AF14: =AB14+AD14 -> 2325.7491
B15: 46298 | C15: Saturday | D15: 238 | I15: =IFERROR(H15/G15,0) -> 0 | J15: =IFERROR(G15/F15,0) -> 0 | K15: =H15*15/115 -> 0 | L15: =H15-K15 -> 0 | N15: =L15-M15 -> 0 | Q15: =IFERROR(P15/G15,0) -> 0 | S15: =IFERROR((R15/G15),0) -> 0 | T15: =P15*15/115 -> 0 | U15: =P15-T15 -> 0 | W15: =IFERROR(V15/G15,0) -> 0 | Y15: =IFERROR((X15/P15),0) -> 0 | AA15: =H15 -> 0 | AB15: =N15 -> 0 | AC15: =P15 -> 0 | AD15: =U15 -> 0 | AE15: =AA15+AC15 -> 0 | AF15: =AB15+AD15 -> 0
B16: 46299 | C16: Sunday | D16: 238 | I16: =IFERROR(H16/G16,0) -> 0 | J16: =IFERROR(G16/F16,0) -> 0 | K16: =H16*15/115 -> 0 | L16: =H16-K16 -> 0 | N16: =L16-M16 -> 0 | Q16: =IFERROR(P16/G16,0) -> 0 | S16: =IFERROR((R16/G16),0) -> 0 | T16: =P16*15/115 -> 0 | U16: =P16-T16 -> 0 | W16: =IFERROR(V16/G16,0) -> 0 | Y16: =IFERROR((X16/P16),0) -> 0 | AA16: =H16 -> 0 | AB16: =N16 -> 0 | AC16: =P16 -> 0 | AD16: =U16 -> 0 | AE16: =AA16+AC16 -> 0 | AF16: =AB16+AD16 -> 0
B17: 46300 | C17: Monday | D17: 238 | I17: =IFERROR(H17/G17,0) -> 0 | J17: =IFERROR(G17/F17,0) -> 0 | K17: =H17*15/115 -> 0 | L17: =H17-K17 -> 0 | N17: =L17-M17 -> 0 | Q17: =IFERROR(P17/G17,0) -> 0 | S17: =IFERROR((R17/G17),0) -> 0 | T17: =P17*15/115 -> 0 | U17: =P17-T17 -> 0 | W17: =IFERROR(V17/G17,0) -> 0 | Y17: =IFERROR((X17/P17),0) -> 0 | AA17: =H17 -> 0 | AB17: =N17 -> 0 | AC17: =P17 -> 0 | AD17: =U17 -> 0 | AE17: =AA17+AC17 -> 0 | AF17: =AB17+AD17 -> 0
B18: 46301 | C18: Tuesday | D18: 238 | I18: =IFERROR(H18/G18,0) -> 0 | J18: =IFERROR(G18/F18,0) -> 0 | K18: =H18*15/115 -> 0 | L18: =H18-K18 -> 0 | N18: =L18-M18 -> 0 | Q18: =IFERROR(P18/G18,0) -> 0 | S18: =IFERROR((R18/G18),0) -> 0 | T18: =P18*15/115 -> 0 | U18: =P18-T18 -> 0 | W18: =IFERROR(V18/G18,0) -> 0 | Y18: =IFERROR((X18/P18),0) -> 0 | AA18: =H18 -> 0 | AB18: =N18 -> 0 | AC18: =P18 -> 0 | AD18: =U18 -> 0 | AE18: =AA18+AC18 -> 0 | AF18: =AB18+AD18 -> 0
B19: 46302 | C19: Wednesday | D19: 238 | I19: =IFERROR(H19/G19,0) -> 0 | J19: =IFERROR(G19/F19,0) -> 0 | K19: =H19*15/115 -> 0 | L19: =H19-K19 -> 0 | N19: =L19-M19 -> 0 | Q19: =IFERROR(P19/G19,0) -> 0 | S19: =IFERROR((R19/G19),0) -> 0 | T19: =P19*15/115 -> 0 | U19: =P19-T19 -> 0 | W19: =IFERROR(V19/G19,0) -> 0 | Y19: =IFERROR((X19/P19),0) -> 0 | AA19: =H19 -> 0 | AB19: =N19 -> 0 | AC19: =P19 -> 0 | AD19: =U19 -> 0 | AE19: =AA19+AC19 -> 0 | AF19: =AB19+AD19 -> 0
B20: 46303 | C20: Thursday | D20: 238 | I20: =IFERROR(H20/G20,0) -> 0 | J20: =IFERROR(G20/F20,0) -> 0 | K20: =H20*15/115 -> 0 | L20: =H20-K20 -> 0 | N20: =L20-M20 -> 0 | Q20: =IFERROR(P20/G20,0) -> 0 | S20: =IFERROR((R20/G20),0) -> 0 | T20: =P20*15/115 -> 0 | U20: =P20-T20 -> 0 | W20: =IFERROR(V20/G20,0) -> 0 | Y20: =IFERROR((X20/P20),0) -> 0 | AA20: =H20 -> 0 | AB20: =N20 -> 0 | AC20: =P20 -> 0 | AD20: =U20 -> 0 | AE20: =AA20+AC20 -> 0 | AF20: =AB20+AD20 -> 0
B21: 46304 | C21: Friday | D21: 238 | I21: =IFERROR(H21/G21,0) -> 0 | J21: =IFERROR(G21/F21,0) -> 0 | K21: =H21*15/115 -> 0 | L21: =H21-K21 -> 0 | N21: =L21-M21 -> 0 | Q21: =IFERROR(P21/G21,0) -> 0 | S21: =IFERROR((R21/G21),0) -> 0 | T21: =P21*15/115 -> 0 | U21: =P21-T21 -> 0 | W21: =IFERROR(V21/G21,0) -> 0 | Y21: =IFERROR((X21/P21),0) -> 0 | AA21: =H21 -> 0 | AB21: =N21 -> 0 | AC21: =P21 -> 0 | AD21: =U21 -> 0 | AE21: =AA21+AC21 -> 0 | AF21: =AB21+AD21 -> 0
B22: 46305 | C22: Saturday | D22: 238 | I22: =IFERROR(H22/G22,0) -> 0 | J22: =IFERROR(G22/F22,0) -> 0 | K22: =H22*15/115 -> 0 | L22: =H22-K22 -> 0 | N22: =L22-M22 -> 0 | Q22: =IFERROR(P22/G22,0) -> 0 | S22: =IFERROR((R22/G22),0) -> 0 | T22: =P22*15/115 -> 0 | U22: =P22-T22 -> 0 | W22: =IFERROR(V22/G22,0) -> 0 | Y22: =IFERROR((X22/P22),0) -> 0 | AA22: =H22 -> 0 | AB22: =N22 -> 0 | AC22: =P22 -> 0 | AD22: =U22 -> 0 | AE22: =AA22+AC22 -> 0 | AF22: =AB22+AD22 -> 0
B23: 46306 | C23: Sunday | D23: 238 | I23: =IFERROR(H23/G23,0) -> 0 | J23: =IFERROR(G23/F23,0) -> 0 | K23: =H23*15/115 -> 0 | L23: =H23-K23 -> 0 | N23: =L23-M23 -> 0 | Q23: =IFERROR(P23/G23,0) -> 0 | S23: =IFERROR((R23/G23),0) -> 0 | T23: =P23*15/115 -> 0 | U23: =P23-T23 -> 0 | W23: =IFERROR(V23/G23,0) -> 0 | Y23: =IFERROR((X23/P23),0) -> 0 | AA23: =H23 -> 0 | AB23: =N23 -> 0 | AC23: =P23 -> 0 | AD23: =U23 -> 0 | AE23: =AA23+AC23 -> 0 | AF23: =AB23+AD23 -> 0
B24: 46307 | C24: Monday | D24: 238 | I24: =IFERROR(H24/G24,0) -> 0 | J24: =IFERROR(G24/F24,0) -> 0 | K24: =H24*15/115 -> 0 | L24: =H24-K24 -> 0 | N24: =L24-M24 -> 0 | Q24: =IFERROR(P24/G24,0) -> 0 | S24: =IFERROR((R24/G24),0) -> 0 | T24: =P24*15/115 -> 0 | U24: =P24-T24 -> 0 | W24: =IFERROR(V24/G24,0) -> 0 | Y24: =IFERROR((X24/P24),0) -> 0 | AA24: =H24 -> 0 | AB24: =N24 -> 0 | AC24: =P24 -> 0 | AD24: =U24 -> 0 | AE24: =AA24+AC24 -> 0 | AF24: =AB24+AD24 -> 0
B25: 46308 | C25: Tuesday | D25: 238 | I25: =IFERROR(H25/G25,0) -> 0 | J25: =IFERROR(G25/F25,0) -> 0 | K25: =H25*15/115 -> 0 | L25: =H25-K25 -> 0 | N25: =L25-M25 -> 0 | Q25: =IFERROR(P25/G25,0) -> 0 | S25: =IFERROR((R25/G25),0) -> 0 | T25: =P25*15/115 -> 0 | U25: =P25-T25 -> 0 | W25: =IFERROR(V25/G25,0) -> 0 | Y25: =IFERROR((X25/P25),0) -> 0 | AA25: =H25 -> 0 | AB25: =N25 -> 0 | AC25: =P25 -> 0 | AD25: =U25 -> 0 | AE25: =AA25+AC25 -> 0 | AF25: =AB25+AD25 -> 0
B26: 46309 | C26: Wednesday | D26: 238 | I26: =IFERROR(H26/G26,0) -> 0 | J26: =IFERROR(G26/F26,0) -> 0 | K26: =H26*15/115 -> 0 | L26: =H26-K26 -> 0 | N26: =L26-M26 -> 0 | Q26: =IFERROR(P26/G26,0) -> 0 | S26: =IFERROR((R26/G26),0) -> 0 | T26: =P26*15/115 -> 0 | U26: =P26-T26 -> 0 | W26: =IFERROR(V26/G26,0) -> 0 | Y26: =IFERROR((X26/P26),0) -> 0 | AA26: =H26 -> 0 | AB26: =N26 -> 0 | AC26: =P26 -> 0 | AD26: =U26 -> 0 | AE26: =AA26+AC26 -> 0 | AF26: =AB26+AD26 -> 0
... B43: 46326 | C43: Saturday | D43: 238 | I43: =IFERROR(H43/G43,0) -> 0 | J43: =IFERROR(G43/F43,0) -> 0 | K43: =H43*15/115 -> 0 | L43: =H43-K43 -> 0 | N43: =L43-M43 -> 0 | Q43: =IFERROR(P43/G43,0) -> 0 | S43: =IFERROR((R43/G43),0) -> 0 | T43: =P43*15/115 -> 0 | U43: =P43-T43 -> 0 | W43: =IFERROR(V43/G43,0) -> 0 | Y43: =IFERROR((X43/P43),0) -> 0 | AA43: =H43 -> 0 | AB43: =N43 -> 0 | AC43: =P43 -> 0 | AD43: =U43 -> 0 | AE43: =AA43+AC43 -> 0 | AF43: =AB43+AD43 -> 0
B44: TOTAL | D44: =AVERAGE(D13:D43) -> 238 | E44: =SUM(E13:E43) -> 34 | F44: =SUM(F13:F43) -> 1978 | G44: =SUM(G13:G43) -> 94 | H44: =SUM(H13:H43) -> 3722 | I44: =IFERROR(H44/G44,0) -> 39.595745 | J44: =IFERROR((G44/F44),0) -> 0.04752275 | K44: =SUM(K13:K43) -> 485.47826 | L44: =SUM(L13:L43) -> 3236.5217 | M44: =SUM(M13:M43) -> 272.32 | N44: =SUM(N13:N43) -> 2964.2017 | P44: =SUM(P13:P43) -> 2520 | Q44: =IFERROR(P44/G44,0) -> 26.808511 | R44: =SUM(R13:R43) -> 60 | S44: =IFERROR((R44/G44),0) -> 0.63829787 | T44: =SUM(T13:T43) -> 328.69565 | U44: =SUM(U13:U43) -> 2191.3043 | V44: =SUM(V13:V43) -> 120 | W44: =IFERROR(V44/G44,0) -> 1.2765957 | X44: =SUM(X13:X43) -> 420.46 | Y44: =IFERROR((X44/P44),0) -> 0.16684921 | AA44: =SUM(AA13:AA43) -> 3722 | AB44: =SUM(AB13:AB43) -> 2964.2017 | AC44: =SUM(AC13:AC43) -> 2520 | AD44: =SUM(AD13:AD43) -> 2191.3043 | AE44: =SUM(AE13:AE43) -> 6242 | AF44: =SUM(AF13:AF43) -> 5155.5061
